{"timestamp":"2021-09-18-15-34-38","name":"OrchardCore-index-html","run":1,"failures":[{"ID":1,"type":"Element-Protrusion","rangeMin":478,"rangeMax":767,"rectangles":[[{"x":15,"y":5073,"width":80,"height":80,"left":15,"top":5073,"right":95,"bottom":5153,"minX":15,"maxX":95,"minY":5073,"maxY":5153,"xpath":"/HTML/BODY/SECTION[3]/DIV/DIV[2]/DIV/UL/LI[6]/DIV","validSize":true,"positiveCoordinates":true,"selector":"html:nth-of-type(1) > body:nth-of-type(1) > section:nth-of-type(3) > div:nth-of-type(1) > div:nth-of-type(2) > div:nth-of-type(1) > ul:nth-of-type(1) > li:nth-of-type(6) > div:nth-of-type(1)"},{"x":15,"y":4195,"width":448,"height":942,"left":15,"top":4195,"right":463,"bottom":5137,"minX":15,"maxX":463,"minY":4195,"maxY":5137,"xpath":"/HTML/BODY/SECTION[3]/DIV/DIV[2]/DIV/UL","validSize":true,"positiveCoordinates":true,"selector":"html:nth-of-type(1) > body:nth-of-type(1) > section:nth-of-type(3) > div:nth-of-type(1) > div:nth-of-type(2) > div:nth-of-type(1) > ul:nth-of-type(1)"}],[{"x":128.5,"y":4232,"width":80,"height":80,"left":128.5,"top":4232,"right":208.5,"bottom":4312,"minX":128.5,"maxX":208.5,"minY":4232,"maxY":4312,"xpath":"/HTML/BODY/SECTION[3]/DIV/DIV[2]/DIV/UL/LI[6]/DIV","validSize":true,"positiveCoordinates":true,"selector":"html:nth-of-type(1) > body:nth-of-type(1) > section:nth-of-type(3) > div:nth-of-type(1) > div:nth-of-type(2) > div:nth-of-type(1) > ul:nth-of-type(1) > li:nth-of-type(6) > div:nth-of-type(1)"},{"x":128.5,"y":3410,"width":510,"height":886,"left":128.5,"top":3410,"right":638.5,"bottom":4296,"minX":128.5,"maxX":638.5,"minY":3410,"maxY":4296,"xpath":"/HTML/BODY/SECTION[3]/DIV/DIV[2]/DIV/UL","validSize":true,"positiveCoordinates":true,"selector":"html:nth-of-type(1) > body:nth-of-type(1) > section:nth-of-type(3) > div:nth-of-type(1) > div:nth-of-type(2) > div:nth-of-type(1) > ul:nth-of-type(1)"}],[{"x":207.8802032470703,"y":2726.09375,"width":62.23957824707031,"height":62.239501953125,"left":207.8802032470703,"top":2726.09375,"right":270.1197814941406,"bottom":2788.333251953125,"minX":207.8802032470703,"maxX":270.1197814941406,"minY":2726.09375,"maxY":2788.333251953125,"xpath":"/HTML/BODY/SECTION[3]/DIV/DIV[2]/DIV/UL/LI[6]/DIV","validSize":true,"positiveCoordinates":true,"selector":"html:nth-of-type(1) > body:nth-of-type(1) > section:nth-of-type(3) > div:nth-of-type(1) > div:nth-of-type(2) > div:nth-of-type(1) > ul:nth-of-type(1) > li:nth-of-type(6) > div:nth-of-type(1)"},{"x":24.2734375,"y":1839.8021240234375,"width":429.453125,"height":955.9998779296875,"left":24.2734375,"top":1839.8021240234375,"right":453.7265625,"bottom":2795.802001953125,"minX":24.2734375,"maxX":453.7265625,"minY":1839.8021240234375,"maxY":2795.802001953125,"xpath":"/HTML/BODY/SECTION[3]/DIV/DIV[2]/DIV/UL","validSize":true,"positiveCoordinates":true,"selector":"html:nth-of-type(1) > body:nth-of-type(1) > section:nth-of-type(3) > div:nth-of-type(1) > div:nth-of-type(2) > div:nth-of-type(1) > ul:nth-of-type(1)"}],[{"x":333.5650939941406,"y":4374.296875,"width":99.86981201171875,"height":99.86962890625,"left":333.5650939941406,"top":4374.296875,"right":433.4349060058594,"bottom":4474.16650390625,"minX":333.5650939941406,"maxX":433.4349060058594,"minY":4374.296875,"maxY":4474.16650390625,"xpath":"/HTML/BODY/SECTION[3]/DIV/DIV[2]/DIV/UL/LI[6]/DIV","validSize":true,"positiveCoordinates":true,"selector":"html:nth-of-type(1) > body:nth-of-type(1) > section:nth-of-type(3) > div:nth-of-type(1) > div:nth-of-type(2) > div:nth-of-type(1) > ul:nth-of-type(1) > li:nth-of-type(6) > div:nth-of-type(1)"},{"x":38.94921875,"y":2952.151123046875,"width":689.1015625,"height":1533.999755859375,"left":38.94921875,"top":2952.151123046875,"right":728.05078125,"bottom":4486.15087890625,"minX":38.94921875,"maxX":728.05078125,"minY":2952.151123046875,"maxY":4486.15087890625,"xpath":"/HTML/BODY/SECTION[3]/DIV/DIV[2]/DIV/UL","validSize":true,"positiveCoordinates":true,"selector":"html:nth-of-type(1) > body:nth-of-type(1) > section:nth-of-type(3) > div:nth-of-type(1) > div:nth-of-type(2) > div:nth-of-type(1) > ul:nth-of-type(1)"}],[{"x":15.03144645690918,"y":5083.63525390625,"width":80.16771125793457,"height":80.16748046875,"left":15.03144645690918,"top":5083.63525390625,"right":95.19915771484375,"bottom":5163.802734375,"minX":15.03144645690918,"maxX":95.19915771484375,"minY":5083.63525390625,"maxY":5163.802734375,"xpath":"/HTML/BODY/SECTION[3]/DIV/DIV[2]/DIV/UL/LI[6]/DIV","validSize":true,"positiveCoordinates":true,"selector":"html:nth-of-type(1) > body:nth-of-type(1) > section:nth-of-type(3) > div:nth-of-type(1) > div:nth-of-type(2) > div:nth-of-type(1) > ul:nth-of-type(1) > li:nth-of-type(6) > div:nth-of-type(1)"},{"x":15.03144645690918,"y":4203.79443359375,"width":447.93712043762207,"height":972.03369140625,"left":15.03144645690918,"top":4203.79443359375,"right":462.96856689453125,"bottom":5175.828125,"minX":15.03144645690918,"maxX":462.96856689453125,"minY":4203.79443359375,"maxY":5175.828125,"xpath":"/HTML/BODY/SECTION[3]/DIV/DIV[2]/DIV/UL","validSize":true,"positiveCoordinates":true,"selector":"html:nth-of-type(1) > body:nth-of-type(1) > section:nth-of-type(3) > div:nth-of-type(1) > div:nth-of-type(2) > div:nth-of-type(1) > ul:nth-of-type(1)"}],[{"x":24.119497299194336,"y":8157.2138671875,"width":128.6373233795166,"height":128.6376953125,"left":24.119497299194336,"top":8157.2138671875,"right":152.75682067871094,"bottom":8285.8515625,"minX":24.119497299194336,"maxX":152.75682067871094,"minY":8157.2138671875,"maxY":8285.8515625,"xpath":"/HTML/BODY/SECTION[3]/DIV/DIV[2]/DIV/UL/LI[6]/DIV","validSize":true,"positiveCoordinates":true,"selector":"html:nth-of-type(1) > body:nth-of-type(1) > section:nth-of-type(3) > div:nth-of-type(1) > div:nth-of-type(2) > div:nth-of-type(1) > ul:nth-of-type(1) > li:nth-of-type(6) > div:nth-of-type(1)"},{"x":24.119497299194336,"y":6745.41943359375,"width":718.7609958648682,"height":1559.72705078125,"left":24.119497299194336,"top":6745.41943359375,"right":742.8804931640625,"bottom":8305.146484375,"minX":24.119497299194336,"maxX":742.8804931640625,"minY":6745.41943359375,"maxY":8305.146484375,"xpath":"/HTML/BODY/SECTION[3]/DIV/DIV[2]/DIV/UL","validSize":true,"positiveCoordinates":true,"selector":"html:nth-of-type(1) > body:nth-of-type(1) > section:nth-of-type(3) > div:nth-of-type(1) > div:nth-of-type(2) > div:nth-of-type(1) > ul:nth-of-type(1)"}]],"anonymizedImageNames":["1-478-F","1-767-F","1-478-W","1-767-W","1-478-N","1-767-N"]},{"ID":2,"type":"Element-Protrusion","rangeMin":992,"rangeMax":1199,"rectangles":[[{"x":428,"y":4261,"width":160,"height":128,"left":428,"top":4261,"right":588,"bottom":4389,"minX":428,"maxX":588,"minY":4261,"maxY":4389,"xpath":"/HTML/BODY/SECTION[3]/DIV/DIV[2]/DIV/UL/LI[6]/DIV/SPAN","validSize":true,"positiveCoordinates":true,"selector":"html:nth-of-type(1) > body:nth-of-type(1) > section:nth-of-type(3) > div:nth-of-type(1) > div:nth-of-type(2) > div:nth-of-type(1) > ul:nth-of-type(1) > li:nth-of-type(6) > div:nth-of-type(1) > span:nth-of-type(1)"},{"x":421,"y":4254,"width":150,"height":150,"left":421,"top":4254,"right":571,"bottom":4404,"minX":421,"maxX":571,"minY":4254,"maxY":4404,"xpath":"/HTML/BODY/SECTION[3]/DIV/DIV[2]/DIV/UL/LI[6]/DIV","validSize":true,"positiveCoordinates":true,"selector":"html:nth-of-type(1) > body:nth-of-type(1) > section:nth-of-type(3) > div:nth-of-type(1) > div:nth-of-type(2) > div:nth-of-type(1) > ul:nth-of-type(1) > li:nth-of-type(6) > div:nth-of-type(1)"}],[{"x":531.5,"y":4261,"width":160,"height":128,"left":531.5,"top":4261,"right":691.5,"bottom":4389,"minX":531.5,"maxX":691.5,"minY":4261,"maxY":4389,"xpath":"/HTML/BODY/SECTION[3]/DIV/DIV[2]/DIV/UL/LI[6]/DIV/SPAN","validSize":true,"positiveCoordinates":true,"selector":"html:nth-of-type(1) > body:nth-of-type(1) > section:nth-of-type(3) > div:nth-of-type(1) > div:nth-of-type(2) > div:nth-of-type(1) > ul:nth-of-type(1) > li:nth-of-type(6) > div:nth-of-type(1) > span:nth-of-type(1)"},{"x":524.5,"y":4254,"width":150,"height":150,"left":524.5,"top":4254,"right":674.5,"bottom":4404,"minX":524.5,"maxX":674.5,"minY":4254,"maxY":4404,"xpath":"/HTML/BODY/SECTION[3]/DIV/DIV[2]/DIV/UL/LI[6]/DIV","validSize":true,"positiveCoordinates":true,"selector":"html:nth-of-type(1) > body:nth-of-type(1) > section:nth-of-type(3) > div:nth-of-type(1) > div:nth-of-type(2) > div:nth-of-type(1) > ul:nth-of-type(1) > li:nth-of-type(6) > div:nth-of-type(1)"}],[{"x":431.5199890136719,"y":3567.066650390625,"width":132.26669311523438,"height":105.813232421875,"left":431.5199890136719,"top":3567.066650390625,"right":563.7866821289062,"bottom":3672.8798828125,"minX":431.5199890136719,"maxX":563.7866821289062,"minY":3567.066650390625,"maxY":3672.8798828125,"xpath":"/HTML/BODY/SECTION[3]/DIV/DIV[2]/DIV/UL/LI[6]/DIV/SPAN","validSize":true,"positiveCoordinates":true,"selector":"html:nth-of-type(1) > body:nth-of-type(1) > section:nth-of-type(3) > div:nth-of-type(1) > div:nth-of-type(2) > div:nth-of-type(1) > ul:nth-of-type(1) > li:nth-of-type(6) > div:nth-of-type(1) > span:nth-of-type(1)"},{"x":425.73333740234375,"y":3561.280029296875,"width":140.5333251953125,"height":140.533203125,"left":425.73333740234375,"top":3561.280029296875,"right":566.2666625976562,"bottom":3701.813232421875,"minX":425.73333740234375,"maxX":566.2666625976562,"minY":3561.280029296875,"maxY":3701.813232421875,"xpath":"/HTML/BODY/SECTION[3]/DIV/DIV[2]/DIV/UL/LI[6]/DIV","validSize":true,"positiveCoordinates":true,"selector":"html:nth-of-type(1) > body:nth-of-type(1) > section:nth-of-type(3) > div:nth-of-type(1) > div:nth-of-type(2) > div:nth-of-type(1) > ul:nth-of-type(1) > li:nth-of-type(6) > div:nth-of-type(1)"}],[{"x":521.5650024414062,"y":4311.404296875,"width":159.86663818359375,"height":127.89306640625,"left":521.5650024414062,"top":4311.404296875,"right":681.431640625,"bottom":4439.29736328125,"minX":521.5650024414062,"maxX":681.431640625,"minY":4311.404296875,"maxY":4439.29736328125,"xpath":"/HTML/BODY/SECTION[3]/DIV/DIV[2]/DIV/UL/LI[6]/DIV/SPAN","validSize":true,"positiveCoordinates":true,"selector":"html:nth-of-type(1) > body:nth-of-type(1) > section:nth-of-type(3) > div:nth-of-type(1) > div:nth-of-type(2) > div:nth-of-type(1) > ul:nth-of-type(1) > li:nth-of-type(6) > div:nth-of-type(1) > span:nth-of-type(1)"},{"x":514.5708618164062,"y":4304.41015625,"width":169.8582763671875,"height":169.8583984375,"left":514.5708618164062,"top":4304.41015625,"right":684.4291381835938,"bottom":4474.2685546875,"minX":514.5708618164062,"maxX":684.4291381835938,"minY":4304.41015625,"maxY":4474.2685546875,"xpath":"/HTML/BODY/SECTION[3]/DIV/DIV[2]/DIV/UL/LI[6]/DIV","validSize":true,"positiveCoordinates":true,"selector":"html:nth-of-type(1) > body:nth-of-type(1) > section:nth-of-type(3) > div:nth-of-type(1) > div:nth-of-type(2) > div:nth-of-type(1) > ul:nth-of-type(1) > li:nth-of-type(6) > div:nth-of-type(1)"}]],"anonymizedImageNames":["2-992-F","2-1199-F","2-992-W","2-1199-W"]},{"ID":3,"type":"Element-Protrusion","rangeMin":339,"rangeMax":991,"rectangles":[[{"x":22,"y":5513,"width":160,"height":128,"left":22,"top":5513,"right":182,"bottom":5641,"minX":22,"maxX":182,"minY":5513,"maxY":5641,"xpath":"/HTML/BODY/SECTION[3]/DIV/DIV[2]/DIV/UL/LI[6]/DIV/SPAN","validSize":true,"positiveCoordinates":true,"selector":"html:nth-of-type(1) > body:nth-of-type(1) > section:nth-of-type(3) > div:nth-of-type(1) > div:nth-of-type(2) > div:nth-of-type(1) > ul:nth-of-type(1) > li:nth-of-type(6) > div:nth-of-type(1) > span:nth-of-type(1)"},{"x":0,"y":4051,"width":339,"height":1563,"left":0,"top":4051,"right":339,"bottom":5614,"minX":0,"maxX":339,"minY":4051,"maxY":5614,"xpath":"/HTML/BODY/SECTION[3]/DIV","validSize":true,"positiveCoordinates":true,"selector":"html:nth-of-type(1) > body:nth-of-type(1) > section:nth-of-type(3) > div:nth-of-type(1)"}],[{"x":452.5,"y":4387,"width":160,"height":128,"left":452.5,"top":4387,"right":612.5,"bottom":4515,"minX":452.5,"maxX":612.5,"minY":4387,"maxY":4515,"xpath":"/HTML/BODY/SECTION[3]/DIV/DIV[2]/DIV/UL/LI[6]/DIV/SPAN","validSize":true,"positiveCoordinates":true,"selector":"html:nth-of-type(1) > body:nth-of-type(1) > section:nth-of-type(3) > div:nth-of-type(1) > div:nth-of-type(2) > div:nth-of-type(1) > ul:nth-of-type(1) > li:nth-of-type(6) > div:nth-of-type(1) > span:nth-of-type(1)"},{"x":135.5,"y":2799,"width":720,"height":1709,"left":135.5,"top":2799,"right":855.5,"bottom":4508,"minX":135.5,"maxX":855.5,"minY":2799,"maxY":4508,"xpath":"/HTML/BODY/SECTION[3]/DIV","validSize":true,"positiveCoordinates":true,"selector":"html:nth-of-type(1) > body:nth-of-type(1) > section:nth-of-type(3) > div:nth-of-type(1)"}],[{"x":146.26210021972656,"y":1456.1280517578125,"width":54.67741394042969,"height":43.741943359375,"left":146.26210021972656,"top":1456.1280517578125,"right":200.93951416015625,"bottom":1499.8699951171875,"minX":146.26210021972656,"maxX":200.93951416015625,"minY":1456.1280517578125,"maxY":1499.8699951171875,"xpath":"/HTML/BODY/SECTION[3]/DIV/DIV[2]/DIV/UL/LI[6]/DIV/SPAN","validSize":true,"positiveCoordinates":true,"selector":"html:nth-of-type(1) > body:nth-of-type(1) > section:nth-of-type(3) > div:nth-of-type(1) > div:nth-of-type(2) > div:nth-of-type(1) > ul:nth-of-type(1) > li:nth-of-type(6) > div:nth-of-type(1) > span:nth-of-type(1)"},{"x":5.467741966247559,"y":966.76513671875,"width":328.06451511383057,"height":543.6986083984375,"left":5.467741966247559,"top":966.76513671875,"right":333.5322570800781,"bottom":1510.4637451171875,"minX":5.467741966247559,"maxX":333.5322570800781,"minY":966.76513671875,"maxY":1510.4637451171875,"xpath":"/HTML/BODY/SECTION[3]/DIV","validSize":true,"positiveCoordinates":true,"selector":"html:nth-of-type(1) > body:nth-of-type(1) > section:nth-of-type(3) > div:nth-of-type(1)"}],[{"x":427.56854248046875,"y":4256.70458984375,"width":159.8387451171875,"height":127.87109375,"left":427.56854248046875,"top":4256.70458984375,"right":587.4072875976562,"bottom":4384.57568359375,"minX":427.56854248046875,"maxX":587.4072875976562,"minY":4256.70458984375,"maxY":4384.57568359375,"xpath":"/HTML/BODY/SECTION[3]/DIV/DIV[2]/DIV/UL/LI[6]/DIV/SPAN","validSize":true,"positiveCoordinates":true,"selector":"html:nth-of-type(1) > body:nth-of-type(1) > section:nth-of-type(3) > div:nth-of-type(1) > div:nth-of-type(2) > div:nth-of-type(1) > ul:nth-of-type(1) > li:nth-of-type(6) > div:nth-of-type(1) > span:nth-of-type(1)"},{"x":15.983870506286621,"y":2826.148193359375,"width":959.0322427749634,"height":1589.396240234375,"left":15.983870506286621,"top":2826.148193359375,"right":975.01611328125,"bottom":4415.54443359375,"minX":15.983870506286621,"maxX":975.01611328125,"minY":2826.148193359375,"maxY":4415.54443359375,"xpath":"/HTML/BODY/SECTION[3]/DIV","validSize":true,"positiveCoordinates":true,"selector":"html:nth-of-type(1) > body:nth-of-type(1) > section:nth-of-type(3) > div:nth-of-type(1)"}],[{"x":22.065088272094727,"y":5527.3046875,"width":160.47337913513184,"height":128.37890625,"left":22.065088272094727,"top":5527.3046875,"right":182.53846740722656,"bottom":5655.68359375,"minX":22.065088272094727,"maxX":182.53846740722656,"minY":5527.3046875,"maxY":5655.68359375,"xpath":"/HTML/BODY/SECTION[3]/DIV/DIV[2]/DIV/UL/LI[6]/DIV/SPAN","validSize":true,"positiveCoordinates":true,"selector":"html:nth-of-type(1) > body:nth-of-type(1) > section:nth-of-type(3) > div:nth-of-type(1) > div:nth-of-type(2) > div:nth-of-type(1) > ul:nth-of-type(1) > li:nth-of-type(6) > div:nth-of-type(1) > span:nth-of-type(1)"},{"x":0,"y":4060.979248046875,"width":339,"height":1595.707275390625,"left":0,"top":4060.979248046875,"right":339,"bottom":5656.6865234375,"minX":0,"maxX":339,"minY":4060.979248046875,"maxY":5656.6865234375,"xpath":"/HTML/BODY/SECTION[3]/DIV","validSize":true,"positiveCoordinates":true,"selector":"html:nth-of-type(1) > body:nth-of-type(1) > section:nth-of-type(3) > div:nth-of-type(1)"}],[{"x":64.50296020507812,"y":16157.9912109375,"width":469.1123962402344,"height":375.2900390625,"left":64.50296020507812,"top":16157.9912109375,"right":533.6153564453125,"bottom":16533.28125,"minX":64.50296020507812,"maxX":533.6153564453125,"minY":16157.9912109375,"maxY":16533.28125,"xpath":"/HTML/BODY/SECTION[3]/DIV/DIV[2]/DIV/UL/LI[6]/DIV/SPAN","validSize":true,"positiveCoordinates":true,"selector":"html:nth-of-type(1) > body:nth-of-type(1) > section:nth-of-type(3) > div:nth-of-type(1) > div:nth-of-type(2) > div:nth-of-type(1) > ul:nth-of-type(1) > li:nth-of-type(6) > div:nth-of-type(1) > span:nth-of-type(1)"},{"x":0,"y":11871.4765625,"width":991,"height":4664.736328125,"left":0,"top":11871.4765625,"right":991,"bottom":16536.212890625,"minX":0,"maxX":991,"minY":11871.4765625,"maxY":16536.212890625,"xpath":"/HTML/BODY/SECTION[3]/DIV","validSize":true,"positiveCoordinates":true,"selector":"html:nth-of-type(1) > body:nth-of-type(1) > section:nth-of-type(3) > div:nth-of-type(1)"}]],"anonymizedImageNames":["3-339-F","3-991-F","3-339-W","3-991-W","3-339-N","3-991-N"]},{"ID":4,"type":"Element-Collision","rangeMin":320,"rangeMax":767,"rectangles":[[{"x":15,"y":5326,"width":80,"height":80,"left":15,"top":5326,"right":95,"bottom":5406,"minX":15,"maxX":95,"minY":5326,"maxY":5406,"xpath":"/HTML/BODY/SECTION[3]/DIV/DIV[2]/DIV/UL/LI[5]/DIV","validSize":true,"positiveCoordinates":true,"selector":"html:nth-of-type(1) > body:nth-of-type(1) > section:nth-of-type(3) > div:nth-of-type(1) > div:nth-of-type(2) > div:nth-of-type(1) > ul:nth-of-type(1) > li:nth-of-type(5) > div:nth-of-type(1)"},{"x":15,"y":5326,"width":290,"height":204,"left":15,"top":5326,"right":305,"bottom":5530,"minX":15,"maxX":305,"minY":5326,"maxY":5530,"xpath":"/HTML/BODY/SECTION[3]/DIV/DIV[2]/DIV/UL/LI[5]/DIV[2]","validSize":true,"positiveCoordinates":true,"selector":"html:nth-of-type(1) > body:nth-of-type(1) > section:nth-of-type(3) > div:nth-of-type(1) > div:nth-of-type(2) > div:nth-of-type(1) > ul:nth-of-type(1) > li:nth-of-type(5) > div:nth-of-type(2)"}],[{"x":128.5,"y":4090,"width":80,"height":80,"left":128.5,"top":4090,"right":208.5,"bottom":4170,"minX":128.5,"maxX":208.5,"minY":4090,"maxY":4170,"xpath":"/HTML/BODY/SECTION[3]/DIV/DIV[2]/DIV/UL/LI[5]/DIV","validSize":true,"positiveCoordinates":true,"selector":"html:nth-of-type(1) > body:nth-of-type(1) > section:nth-of-type(3) > div:nth-of-type(1) > div:nth-of-type(2) > div:nth-of-type(1) > ul:nth-of-type(1) > li:nth-of-type(5) > div:nth-of-type(1)"},{"x":128.5,"y":4090,"width":510,"height":92,"left":128.5,"top":4090,"right":638.5,"bottom":4182,"minX":128.5,"maxX":638.5,"minY":4090,"maxY":4182,"xpath":"/HTML/BODY/SECTION[3]/DIV/DIV[2]/DIV/UL/LI[5]/DIV[2]","validSize":true,"positiveCoordinates":true,"selector":"html:nth-of-type(1) > body:nth-of-type(1) > section:nth-of-type(3) > div:nth-of-type(1) > div:nth-of-type(2) > div:nth-of-type(1) > ul:nth-of-type(1) > li:nth-of-type(5) > div:nth-of-type(2)"}],[{"x":139.1666717529297,"y":1713.3333740234375,"width":41.666656494140625,"height":41.6666259765625,"left":139.1666717529297,"top":1713.3333740234375,"right":180.8333282470703,"bottom":1755,"minX":139.1666717529297,"maxX":180.8333282470703,"minY":1713.3333740234375,"maxY":1755,"xpath":"/HTML/BODY/SECTION[3]/DIV/DIV[2]/DIV/UL/LI[5]/DIV","validSize":true,"positiveCoordinates":true,"selector":"html:nth-of-type(1) > body:nth-of-type(1) > section:nth-of-type(3) > div:nth-of-type(1) > div:nth-of-type(2) > div:nth-of-type(1) > ul:nth-of-type(1) > li:nth-of-type(5) > div:nth-of-type(1)"},{"x":16.25,"y":1713.3333740234375,"width":117.87109375,"height":70,"left":16.25,"top":1713.3333740234375,"right":134.12109375,"bottom":1783.3333740234375,"minX":16.25,"maxX":134.12109375,"minY":1713.3333740234375,"maxY":1783.3333740234375,"xpath":"/HTML/BODY/SECTION[3]/DIV/DIV[2]/DIV/UL/LI[5]/DIV[2]","validSize":true,"positiveCoordinates":true,"selector":"html:nth-of-type(1) > body:nth-of-type(1) > section:nth-of-type(3) > div:nth-of-type(1) > div:nth-of-type(2) > div:nth-of-type(1) > ul:nth-of-type(1) > li:nth-of-type(5) > div:nth-of-type(2)"}],[{"x":333.5650939941406,"y":4106.64599609375,"width":99.86981201171875,"height":99.86962890625,"left":333.5650939941406,"top":4106.64599609375,"right":433.4349060058594,"bottom":4206.515625,"minX":333.5650939941406,"maxX":433.4349060058594,"minY":4106.64599609375,"maxY":4206.515625,"xpath":"/HTML/BODY/SECTION[3]/DIV/DIV[2]/DIV/UL/LI[5]/DIV","validSize":true,"positiveCoordinates":true,"selector":"html:nth-of-type(1) > body:nth-of-type(1) > section:nth-of-type(3) > div:nth-of-type(1) > div:nth-of-type(2) > div:nth-of-type(1) > ul:nth-of-type(1) > li:nth-of-type(5) > div:nth-of-type(1)"},{"x":38.94921875,"y":4106.64599609375,"width":282.52227783203125,"height":167.78125,"left":38.94921875,"top":4106.64599609375,"right":321.47149658203125,"bottom":4274.42724609375,"minX":38.94921875,"maxX":321.47149658203125,"minY":4106.64599609375,"maxY":4274.42724609375,"xpath":"/HTML/BODY/SECTION[3]/DIV/DIV[2]/DIV/UL/LI[5]/DIV[2]","validSize":true,"positiveCoordinates":true,"selector":"html:nth-of-type(1) > body:nth-of-type(1) > section:nth-of-type(3) > div:nth-of-type(1) > div:nth-of-type(2) > div:nth-of-type(1) > ul:nth-of-type(1) > li:nth-of-type(5) > div:nth-of-type(2)"}]],"anonymizedImageNames":["4-320-F","4-767-F","4-320-W","4-767-W"]},{"ID":5,"type":"Element-Protrusion","rangeMin":768,"rangeMax":1199,"rectangles":[[{"x":341,"y":4119,"width":160,"height":128,"left":341,"top":4119,"right":501,"bottom":4247,"minX":341,"maxX":501,"minY":4119,"maxY":4247,"xpath":"/HTML/BODY/SECTION[3]/DIV/DIV[2]/DIV/UL/LI[5]/DIV/SPAN","validSize":true,"positiveCoordinates":true,"selector":"html:nth-of-type(1) > body:nth-of-type(1) > section:nth-of-type(3) > div:nth-of-type(1) > div:nth-of-type(2) > div:nth-of-type(1) > ul:nth-of-type(1) > li:nth-of-type(5) > div:nth-of-type(1) > span:nth-of-type(1)"},{"x":334,"y":4112,"width":100,"height":100,"left":334,"top":4112,"right":434,"bottom":4212,"minX":334,"maxX":434,"minY":4112,"maxY":4212,"xpath":"/HTML/BODY/SECTION[3]/DIV/DIV[2]/DIV/UL/LI[5]/DIV","validSize":true,"positiveCoordinates":true,"selector":"html:nth-of-type(1) > body:nth-of-type(1) > section:nth-of-type(3) > div:nth-of-type(1) > div:nth-of-type(2) > div:nth-of-type(1) > ul:nth-of-type(1) > li:nth-of-type(5) > div:nth-of-type(1)"}],[{"x":531.5,"y":4011,"width":160,"height":128,"left":531.5,"top":4011,"right":691.5,"bottom":4139,"minX":531.5,"maxX":691.5,"minY":4011,"maxY":4139,"xpath":"/HTML/BODY/SECTION[3]/DIV/DIV[2]/DIV/UL/LI[5]/DIV/SPAN","validSize":true,"positiveCoordinates":true,"selector":"html:nth-of-type(1) > body:nth-of-type(1) > section:nth-of-type(3) > div:nth-of-type(1) > div:nth-of-type(2) > div:nth-of-type(1) > ul:nth-of-type(1) > li:nth-of-type(5) > div:nth-of-type(1) > span:nth-of-type(1)"},{"x":524.5,"y":4004,"width":150,"height":150,"left":524.5,"top":4004,"right":674.5,"bottom":4154,"minX":524.5,"maxX":674.5,"minY":4004,"maxY":4154,"xpath":"/HTML/BODY/SECTION[3]/DIV/DIV[2]/DIV/UL/LI[5]/DIV","validSize":true,"positiveCoordinates":true,"selector":"html:nth-of-type(1) > body:nth-of-type(1) > section:nth-of-type(3) > div:nth-of-type(1) > div:nth-of-type(2) > div:nth-of-type(1) > ul:nth-of-type(1) > li:nth-of-type(5) > div:nth-of-type(1)"}],[{"x":334.0799865722656,"y":2588.800048828125,"width":102.4000244140625,"height":81.919921875,"left":334.0799865722656,"top":2588.800048828125,"right":436.4800109863281,"bottom":2670.719970703125,"minX":334.0799865722656,"maxX":436.4800109863281,"minY":2588.800048828125,"maxY":2670.719970703125,"xpath":"/HTML/BODY/SECTION[3]/DIV/DIV[2]/DIV/UL/LI[5]/DIV/SPAN","validSize":true,"positiveCoordinates":true,"selector":"html:nth-of-type(1) > body:nth-of-type(1) > section:nth-of-type(3) > div:nth-of-type(1) > div:nth-of-type(2) > div:nth-of-type(1) > ul:nth-of-type(1) > li:nth-of-type(5) > div:nth-of-type(1) > span:nth-of-type(1)"},{"x":329.6000061035156,"y":2584.320068359375,"width":108.79998779296875,"height":108.800048828125,"left":329.6000061035156,"top":2584.320068359375,"right":438.3999938964844,"bottom":2693.1201171875,"minX":329.6000061035156,"maxX":438.3999938964844,"minY":2584.320068359375,"maxY":2693.1201171875,"xpath":"/HTML/BODY/SECTION[3]/DIV/DIV[2]/DIV/UL/LI[5]/DIV","validSize":true,"positiveCoordinates":true,"selector":"html:nth-of-type(1) > body:nth-of-type(1) > section:nth-of-type(3) > div:nth-of-type(1) > div:nth-of-type(2) > div:nth-of-type(1) > ul:nth-of-type(1) > li:nth-of-type(5) > div:nth-of-type(1)"}],[{"x":521.5650024414062,"y":4041.629150390625,"width":159.86663818359375,"height":127.893310546875,"left":521.5650024414062,"top":4041.629150390625,"right":681.431640625,"bottom":4169.5224609375,"minX":521.5650024414062,"maxX":681.431640625,"minY":4041.629150390625,"maxY":4169.5224609375,"xpath":"/HTML/BODY/SECTION[3]/DIV/DIV[2]/DIV/UL/LI[5]/DIV/SPAN","validSize":true,"positiveCoordinates":true,"selector":"html:nth-of-type(1) > body:nth-of-type(1) > section:nth-of-type(3) > div:nth-of-type(1) > div:nth-of-type(2) > div:nth-of-type(1) > ul:nth-of-type(1) > li:nth-of-type(5) > div:nth-of-type(1) > span:nth-of-type(1)"},{"x":514.5708618164062,"y":4034.635009765625,"width":169.8582763671875,"height":169.858154296875,"left":514.5708618164062,"top":4034.635009765625,"right":684.4291381835938,"bottom":4204.4931640625,"minX":514.5708618164062,"maxX":684.4291381835938,"minY":4034.635009765625,"maxY":4204.4931640625,"xpath":"/HTML/BODY/SECTION[3]/DIV/DIV[2]/DIV/UL/LI[5]/DIV","validSize":true,"positiveCoordinates":true,"selector":"html:nth-of-type(1) > body:nth-of-type(1) > section:nth-of-type(3) > div:nth-of-type(1) > div:nth-of-type(2) > div:nth-of-type(1) > ul:nth-of-type(1) > li:nth-of-type(5) > div:nth-of-type(1)"}]],"anonymizedImageNames":["5-768-F","5-1199-F","5-768-W","5-1199-W"]},{"ID":6,"type":"Element-Protrusion","rangeMin":406,"rangeMax":767,"rectangles":[[{"x":22,"y":5071,"width":160,"height":128,"left":22,"top":5071,"right":182,"bottom":5199,"minX":22,"maxX":182,"minY":5071,"maxY":5199,"xpath":"/HTML/BODY/SECTION[3]/DIV/DIV[2]/DIV/UL/LI[5]/DIV/SPAN","validSize":true,"positiveCoordinates":true,"selector":"html:nth-of-type(1) > body:nth-of-type(1) > section:nth-of-type(3) > div:nth-of-type(1) > div:nth-of-type(2) > div:nth-of-type(1) > ul:nth-of-type(1) > li:nth-of-type(5) > div:nth-of-type(1) > span:nth-of-type(1)"},{"x":15,"y":5064,"width":376,"height":120,"left":15,"top":5064,"right":391,"bottom":5184,"minX":15,"maxX":391,"minY":5064,"maxY":5184,"xpath":"/HTML/BODY/SECTION[3]/DIV/DIV[2]/DIV/UL/LI[5]","validSize":true,"positiveCoordinates":true,"selector":"html:nth-of-type(1) > body:nth-of-type(1) > section:nth-of-type(3) > div:nth-of-type(1) > div:nth-of-type(2) > div:nth-of-type(1) > ul:nth-of-type(1) > li:nth-of-type(5)"}],[{"x":135.5,"y":4097,"width":160,"height":128,"left":135.5,"top":4097,"right":295.5,"bottom":4225,"minX":135.5,"maxX":295.5,"minY":4097,"maxY":4225,"xpath":"/HTML/BODY/SECTION[3]/DIV/DIV[2]/DIV/UL/LI[5]/DIV/SPAN","validSize":true,"positiveCoordinates":true,"selector":"html:nth-of-type(1) > body:nth-of-type(1) > section:nth-of-type(3) > div:nth-of-type(1) > div:nth-of-type(2) > div:nth-of-type(1) > ul:nth-of-type(1) > li:nth-of-type(5) > div:nth-of-type(1) > span:nth-of-type(1)"},{"x":128.5,"y":4090,"width":510,"height":92,"left":128.5,"top":4090,"right":638.5,"bottom":4182,"minX":128.5,"maxX":638.5,"minY":4090,"maxY":4182,"xpath":"/HTML/BODY/SECTION[3]/DIV/DIV[2]/DIV/UL/LI[5]","validSize":true,"positiveCoordinates":true,"selector":"html:nth-of-type(1) > body:nth-of-type(1) > section:nth-of-type(3) > div:nth-of-type(1) > div:nth-of-type(2) > div:nth-of-type(1) > ul:nth-of-type(1) > li:nth-of-type(5)"}],[{"x":180.2682342529297,"y":2177.4921875,"width":84.58332824707031,"height":67.666748046875,"left":180.2682342529297,"top":2177.4921875,"right":264.8515625,"bottom":2245.158935546875,"minX":180.2682342529297,"maxX":264.8515625,"minY":2177.4921875,"maxY":2245.158935546875,"xpath":"/HTML/BODY/SECTION[3]/DIV/DIV[2]/DIV/UL/LI[5]/DIV/SPAN","validSize":true,"positiveCoordinates":true,"selector":"html:nth-of-type(1) > body:nth-of-type(1) > section:nth-of-type(3) > div:nth-of-type(1) > div:nth-of-type(2) > div:nth-of-type(1) > ul:nth-of-type(1) > li:nth-of-type(5) > div:nth-of-type(1) > span:nth-of-type(1)"},{"x":20.6171875,"y":2173.791748046875,"width":364.765625,"height":88.8125,"left":20.6171875,"top":2173.791748046875,"right":385.3828125,"bottom":2262.604248046875,"minX":20.6171875,"maxX":385.3828125,"minY":2173.791748046875,"maxY":2262.604248046875,"xpath":"/HTML/BODY/SECTION[3]/DIV/DIV[2]/DIV/UL/LI[5]","validSize":true,"positiveCoordinates":true,"selector":"html:nth-of-type(1) > body:nth-of-type(1) > section:nth-of-type(3) > div:nth-of-type(1) > div:nth-of-type(2) > div:nth-of-type(1) > ul:nth-of-type(1) > li:nth-of-type(5)"}],[{"x":340.5559997558594,"y":4113.63671875,"width":159.79165649414062,"height":127.83349609375,"left":340.5559997558594,"top":4113.63671875,"right":500.34765625,"bottom":4241.47021484375,"minX":340.5559997558594,"maxX":500.34765625,"minY":4113.63671875,"maxY":4241.47021484375,"xpath":"/HTML/BODY/SECTION[3]/DIV/DIV[2]/DIV/UL/LI[5]/DIV/SPAN","validSize":true,"positiveCoordinates":true,"selector":"html:nth-of-type(1) > body:nth-of-type(1) > section:nth-of-type(3) > div:nth-of-type(1) > div:nth-of-type(2) > div:nth-of-type(1) > ul:nth-of-type(1) > li:nth-of-type(5) > div:nth-of-type(1) > span:nth-of-type(1)"},{"x":38.94921875,"y":4106.64599609375,"width":689.1015625,"height":167.78125,"left":38.94921875,"top":4106.64599609375,"right":728.05078125,"bottom":4274.42724609375,"minX":38.94921875,"maxX":728.05078125,"minY":4106.64599609375,"maxY":4274.42724609375,"xpath":"/HTML/BODY/SECTION[3]/DIV/DIV[2]/DIV/UL/LI[5]","validSize":true,"positiveCoordinates":true,"selector":"html:nth-of-type(1) > body:nth-of-type(1) > section:nth-of-type(3) > div:nth-of-type(1) > div:nth-of-type(2) > div:nth-of-type(1) > ul:nth-of-type(1) > li:nth-of-type(5)"}],[{"x":22.0543212890625,"y":5081.51611328125,"width":160.3950653076172,"height":128.31591796875,"left":22.0543212890625,"top":5081.51611328125,"right":182.4493865966797,"bottom":5209.83203125,"minX":22.0543212890625,"maxX":182.4493865966797,"minY":5081.51611328125,"maxY":5209.83203125,"xpath":"/HTML/BODY/SECTION[3]/DIV/DIV[2]/DIV/UL/LI[5]/DIV/SPAN","validSize":true,"positiveCoordinates":true,"selector":"html:nth-of-type(1) > body:nth-of-type(1) > section:nth-of-type(3) > div:nth-of-type(1) > div:nth-of-type(2) > div:nth-of-type(1) > ul:nth-of-type(1) > li:nth-of-type(5) > div:nth-of-type(1) > span:nth-of-type(1)"},{"x":15.037036895751953,"y":5074.49853515625,"width":375.9259147644043,"height":148.36572265625,"left":15.037036895751953,"top":5074.49853515625,"right":390.96295166015625,"bottom":5222.8642578125,"minX":15.037036895751953,"maxX":390.96295166015625,"minY":5074.49853515625,"maxY":5222.8642578125,"xpath":"/HTML/BODY/SECTION[3]/DIV/DIV[2]/DIV/UL/LI[5]","validSize":true,"positiveCoordinates":true,"selector":"html:nth-of-type(1) > body:nth-of-type(1) > section:nth-of-type(3) > div:nth-of-type(1) > div:nth-of-type(2) > div:nth-of-type(1) > ul:nth-of-type(1) > li:nth-of-type(5)"}],[{"x":41.6641960144043,"y":9599.8095703125,"width":303.0123481750488,"height":242.41015625,"left":41.6641960144043,"top":9599.8095703125,"right":344.6765441894531,"bottom":9842.2197265625,"minX":41.6641960144043,"maxX":344.6765441894531,"minY":9599.8095703125,"maxY":9842.2197265625,"xpath":"/HTML/BODY/SECTION[3]/DIV/DIV[2]/DIV/UL/LI[5]/DIV/SPAN","validSize":true,"positiveCoordinates":true,"selector":"html:nth-of-type(1) > body:nth-of-type(1) > section:nth-of-type(3) > div:nth-of-type(1) > div:nth-of-type(2) > div:nth-of-type(1) > ul:nth-of-type(1) > li:nth-of-type(5) > div:nth-of-type(1) > span:nth-of-type(1)"},{"x":28.407407760620117,"y":9586.552734375,"width":710.1851825714111,"height":280.287109375,"left":28.407407760620117,"top":9586.552734375,"right":738.5925903320312,"bottom":9866.83984375,"minX":28.407407760620117,"maxX":738.5925903320312,"minY":9586.552734375,"maxY":9866.83984375,"xpath":"/HTML/BODY/SECTION[3]/DIV/DIV[2]/DIV/UL/LI[5]","validSize":true,"positiveCoordinates":true,"selector":"html:nth-of-type(1) > body:nth-of-type(1) > section:nth-of-type(3) > div:nth-of-type(1) > div:nth-of-type(2) > div:nth-of-type(1) > ul:nth-of-type(1) > li:nth-of-type(5)"}]],"anonymizedImageNames":["6-406-F","6-767-F","6-406-W","6-767-W","6-406-N","6-767-N"]},{"ID":7,"type":"Element-Collision","rangeMin":320,"rangeMax":767,"rectangles":[[{"x":15,"y":5072,"width":80,"height":80,"left":15,"top":5072,"right":95,"bottom":5152,"minX":15,"maxX":95,"minY":5072,"maxY":5152,"xpath":"/HTML/BODY/SECTION[3]/DIV/DIV[2]/DIV/UL/LI[4]/DIV","validSize":true,"positiveCoordinates":true,"selector":"html:nth-of-type(1) > body:nth-of-type(1) > section:nth-of-type(3) > div:nth-of-type(1) > div:nth-of-type(2) > div:nth-of-type(1) > ul:nth-of-type(1) > li:nth-of-type(4) > div:nth-of-type(1)"},{"x":15,"y":5072,"width":290,"height":204,"left":15,"top":5072,"right":305,"bottom":5276,"minX":15,"maxX":305,"minY":5072,"maxY":5276,"xpath":"/HTML/BODY/SECTION[3]/DIV/DIV[2]/DIV/UL/LI[4]/DIV[2]","validSize":true,"positiveCoordinates":true,"selector":"html:nth-of-type(1) > body:nth-of-type(1) > section:nth-of-type(3) > div:nth-of-type(1) > div:nth-of-type(2) > div:nth-of-type(1) > ul:nth-of-type(1) > li:nth-of-type(4) > div:nth-of-type(2)"}],[{"x":128.5,"y":3920,"width":80,"height":80,"left":128.5,"top":3920,"right":208.5,"bottom":4000,"minX":128.5,"maxX":208.5,"minY":3920,"maxY":4000,"xpath":"/HTML/BODY/SECTION[3]/DIV/DIV[2]/DIV/UL/LI[4]/DIV","validSize":true,"positiveCoordinates":true,"selector":"html:nth-of-type(1) > body:nth-of-type(1) > section:nth-of-type(3) > div:nth-of-type(1) > div:nth-of-type(2) > div:nth-of-type(1) > ul:nth-of-type(1) > li:nth-of-type(4) > div:nth-of-type(1)"},{"x":128.5,"y":3920,"width":510,"height":120,"left":128.5,"top":3920,"right":638.5,"bottom":4040,"minX":128.5,"maxX":638.5,"minY":3920,"maxY":4040,"xpath":"/HTML/BODY/SECTION[3]/DIV/DIV[2]/DIV/UL/LI[4]/DIV[2]","validSize":true,"positiveCoordinates":true,"selector":"html:nth-of-type(1) > body:nth-of-type(1) > section:nth-of-type(3) > div:nth-of-type(1) > div:nth-of-type(2) > div:nth-of-type(1) > ul:nth-of-type(1) > li:nth-of-type(4) > div:nth-of-type(2)"}],[{"x":139.1666717529297,"y":1601.6666259765625,"width":41.666656494140625,"height":41.666748046875,"left":139.1666717529297,"top":1601.6666259765625,"right":180.8333282470703,"bottom":1643.3333740234375,"minX":139.1666717529297,"maxX":180.8333282470703,"minY":1601.6666259765625,"maxY":1643.3333740234375,"xpath":"/HTML/BODY/SECTION[3]/DIV/DIV[2]/DIV/UL/LI[4]/DIV","validSize":true,"positiveCoordinates":true,"selector":"html:nth-of-type(1) > body:nth-of-type(1) > section:nth-of-type(3) > div:nth-of-type(1) > div:nth-of-type(2) > div:nth-of-type(1) > ul:nth-of-type(1) > li:nth-of-type(4) > div:nth-of-type(1)"},{"x":185.87890625,"y":1601.6666259765625,"width":117.87109375,"height":70,"left":185.87890625,"top":1601.6666259765625,"right":303.75,"bottom":1671.6666259765625,"minX":185.87890625,"maxX":303.75,"minY":1601.6666259765625,"maxY":1671.6666259765625,"xpath":"/HTML/BODY/SECTION[3]/DIV/DIV[2]/DIV/UL/LI[4]/DIV[2]","validSize":true,"positiveCoordinates":true,"selector":"html:nth-of-type(1) > body:nth-of-type(1) > section:nth-of-type(3) > div:nth-of-type(1) > div:nth-of-type(2) > div:nth-of-type(1) > ul:nth-of-type(1) > li:nth-of-type(4) > div:nth-of-type(2)"}],[{"x":333.5650939941406,"y":3838.994873046875,"width":99.86981201171875,"height":99.86962890625,"left":333.5650939941406,"top":3838.994873046875,"right":433.4349060058594,"bottom":3938.864501953125,"minX":333.5650939941406,"maxX":433.4349060058594,"minY":3838.994873046875,"maxY":3938.864501953125,"xpath":"/HTML/BODY/SECTION[3]/DIV/DIV[2]/DIV/UL/LI[4]/DIV","validSize":true,"positiveCoordinates":true,"selector":"html:nth-of-type(1) > body:nth-of-type(1) > section:nth-of-type(3) > div:nth-of-type(1) > div:nth-of-type(2) > div:nth-of-type(1) > ul:nth-of-type(1) > li:nth-of-type(4) > div:nth-of-type(1)"},{"x":445.52850341796875,"y":3838.994873046875,"width":282.52227783203125,"height":167.78125,"left":445.52850341796875,"top":3838.994873046875,"right":728.05078125,"bottom":4006.776123046875,"minX":445.52850341796875,"maxX":728.05078125,"minY":3838.994873046875,"maxY":4006.776123046875,"xpath":"/HTML/BODY/SECTION[3]/DIV/DIV[2]/DIV/UL/LI[4]/DIV[2]","validSize":true,"positiveCoordinates":true,"selector":"html:nth-of-type(1) > body:nth-of-type(1) > section:nth-of-type(3) > div:nth-of-type(1) > div:nth-of-type(2) > div:nth-of-type(1) > ul:nth-of-type(1) > li:nth-of-type(4) > div:nth-of-type(2)"}]],"anonymizedImageNames":["7-320-F","7-767-F","7-320-W","7-767-W"]},{"ID":8,"type":"Element-Protrusion","rangeMin":768,"rangeMax":1199,"rectangles":[[{"x":341,"y":3851,"width":160,"height":128,"left":341,"top":3851,"right":501,"bottom":3979,"minX":341,"maxX":501,"minY":3851,"maxY":3979,"xpath":"/HTML/BODY/SECTION[3]/DIV/DIV[2]/DIV/UL/LI[4]/DIV/SPAN","validSize":true,"positiveCoordinates":true,"selector":"html:nth-of-type(1) > body:nth-of-type(1) > section:nth-of-type(3) > div:nth-of-type(1) > div:nth-of-type(2) > div:nth-of-type(1) > ul:nth-of-type(1) > li:nth-of-type(4) > div:nth-of-type(1) > span:nth-of-type(1)"},{"x":334,"y":3844,"width":100,"height":100,"left":334,"top":3844,"right":434,"bottom":3944,"minX":334,"maxX":434,"minY":3844,"maxY":3944,"xpath":"/HTML/BODY/SECTION[3]/DIV/DIV[2]/DIV/UL/LI[4]/DIV","validSize":true,"positiveCoordinates":true,"selector":"html:nth-of-type(1) > body:nth-of-type(1) > section:nth-of-type(3) > div:nth-of-type(1) > div:nth-of-type(2) > div:nth-of-type(1) > ul:nth-of-type(1) > li:nth-of-type(4) > div:nth-of-type(1)"}],[{"x":531.5,"y":3761,"width":160,"height":128,"left":531.5,"top":3761,"right":691.5,"bottom":3889,"minX":531.5,"maxX":691.5,"minY":3761,"maxY":3889,"xpath":"/HTML/BODY/SECTION[3]/DIV/DIV[2]/DIV/UL/LI[4]/DIV/SPAN","validSize":true,"positiveCoordinates":true,"selector":"html:nth-of-type(1) > body:nth-of-type(1) > section:nth-of-type(3) > div:nth-of-type(1) > div:nth-of-type(2) > div:nth-of-type(1) > ul:nth-of-type(1) > li:nth-of-type(4) > div:nth-of-type(1) > span:nth-of-type(1)"},{"x":524.5,"y":3754,"width":150,"height":150,"left":524.5,"top":3754,"right":674.5,"bottom":3904,"minX":524.5,"maxX":674.5,"minY":3754,"maxY":3904,"xpath":"/HTML/BODY/SECTION[3]/DIV/DIV[2]/DIV/UL/LI[4]/DIV","validSize":true,"positiveCoordinates":true,"selector":"html:nth-of-type(1) > body:nth-of-type(1) > section:nth-of-type(3) > div:nth-of-type(1) > div:nth-of-type(2) > div:nth-of-type(1) > ul:nth-of-type(1) > li:nth-of-type(4) > div:nth-of-type(1)"}],[{"x":334.0799865722656,"y":2416,"width":102.4000244140625,"height":81.919921875,"left":334.0799865722656,"top":2416,"right":436.4800109863281,"bottom":2497.919921875,"minX":334.0799865722656,"maxX":436.4800109863281,"minY":2416,"maxY":2497.919921875,"xpath":"/HTML/BODY/SECTION[3]/DIV/DIV[2]/DIV/UL/LI[4]/DIV/SPAN","validSize":true,"positiveCoordinates":true,"selector":"html:nth-of-type(1) > body:nth-of-type(1) > section:nth-of-type(3) > div:nth-of-type(1) > div:nth-of-type(2) > div:nth-of-type(1) > ul:nth-of-type(1) > li:nth-of-type(4) > div:nth-of-type(1) > span:nth-of-type(1)"},{"x":329.6000061035156,"y":2411.52001953125,"width":108.79998779296875,"height":108.800048828125,"left":329.6000061035156,"top":2411.52001953125,"right":438.3999938964844,"bottom":2520.320068359375,"minX":329.6000061035156,"maxX":438.3999938964844,"minY":2411.52001953125,"maxY":2520.320068359375,"xpath":"/HTML/BODY/SECTION[3]/DIV/DIV[2]/DIV/UL/LI[4]/DIV","validSize":true,"positiveCoordinates":true,"selector":"html:nth-of-type(1) > body:nth-of-type(1) > section:nth-of-type(3) > div:nth-of-type(1) > div:nth-of-type(2) > div:nth-of-type(1) > ul:nth-of-type(1) > li:nth-of-type(4) > div:nth-of-type(1)"}],[{"x":521.5650024414062,"y":3771.854248046875,"width":159.86663818359375,"height":127.893310546875,"left":521.5650024414062,"top":3771.854248046875,"right":681.431640625,"bottom":3899.74755859375,"minX":521.5650024414062,"maxX":681.431640625,"minY":3771.854248046875,"maxY":3899.74755859375,"xpath":"/HTML/BODY/SECTION[3]/DIV/DIV[2]/DIV/UL/LI[4]/DIV/SPAN","validSize":true,"positiveCoordinates":true,"selector":"html:nth-of-type(1) > body:nth-of-type(1) > section:nth-of-type(3) > div:nth-of-type(1) > div:nth-of-type(2) > div:nth-of-type(1) > ul:nth-of-type(1) > li:nth-of-type(4) > div:nth-of-type(1) > span:nth-of-type(1)"},{"x":514.5708618164062,"y":3764.860107421875,"width":169.8582763671875,"height":169.858154296875,"left":514.5708618164062,"top":3764.860107421875,"right":684.4291381835938,"bottom":3934.71826171875,"minX":514.5708618164062,"maxX":684.4291381835938,"minY":3764.860107421875,"maxY":3934.71826171875,"xpath":"/HTML/BODY/SECTION[3]/DIV/DIV[2]/DIV/UL/LI[4]/DIV","validSize":true,"positiveCoordinates":true,"selector":"html:nth-of-type(1) > body:nth-of-type(1) > section:nth-of-type(3) > div:nth-of-type(1) > div:nth-of-type(2) > div:nth-of-type(1) > ul:nth-of-type(1) > li:nth-of-type(4) > div:nth-of-type(1)"}]],"anonymizedImageNames":["8-768-F","8-1199-F","8-768-W","8-1199-W"]},{"ID":9,"type":"Element-Protrusion","rangeMin":447,"rangeMax":767,"rectangles":[[{"x":22,"y":4818,"width":160,"height":128,"left":22,"top":4818,"right":182,"bottom":4946,"minX":22,"maxX":182,"minY":4818,"maxY":4946,"xpath":"/HTML/BODY/SECTION[3]/DIV/DIV[2]/DIV/UL/LI[4]/DIV/SPAN","validSize":true,"positiveCoordinates":true,"selector":"html:nth-of-type(1) > body:nth-of-type(1) > section:nth-of-type(3) > div:nth-of-type(1) > div:nth-of-type(2) > div:nth-of-type(1) > ul:nth-of-type(1) > li:nth-of-type(4) > div:nth-of-type(1) > span:nth-of-type(1)"},{"x":15,"y":4811,"width":417,"height":120,"left":15,"top":4811,"right":432,"bottom":4931,"minX":15,"maxX":432,"minY":4811,"maxY":4931,"xpath":"/HTML/BODY/SECTION[3]/DIV/DIV[2]/DIV/UL/LI[4]","validSize":true,"positiveCoordinates":true,"selector":"html:nth-of-type(1) > body:nth-of-type(1) > section:nth-of-type(3) > div:nth-of-type(1) > div:nth-of-type(2) > div:nth-of-type(1) > ul:nth-of-type(1) > li:nth-of-type(4)"}],[{"x":135.5,"y":3927,"width":160,"height":128,"left":135.5,"top":3927,"right":295.5,"bottom":4055,"minX":135.5,"maxX":295.5,"minY":3927,"maxY":4055,"xpath":"/HTML/BODY/SECTION[3]/DIV/DIV[2]/DIV/UL/LI[4]/DIV/SPAN","validSize":true,"positiveCoordinates":true,"selector":"html:nth-of-type(1) > body:nth-of-type(1) > section:nth-of-type(3) > div:nth-of-type(1) > div:nth-of-type(2) > div:nth-of-type(1) > ul:nth-of-type(1) > li:nth-of-type(4) > div:nth-of-type(1) > span:nth-of-type(1)"},{"x":128.5,"y":3920,"width":510,"height":120,"left":128.5,"top":3920,"right":638.5,"bottom":4040,"minX":128.5,"maxX":638.5,"minY":3920,"maxY":4040,"xpath":"/HTML/BODY/SECTION[3]/DIV/DIV[2]/DIV/UL/LI[4]","validSize":true,"positiveCoordinates":true,"selector":"html:nth-of-type(1) > body:nth-of-type(1) > section:nth-of-type(3) > div:nth-of-type(1) > div:nth-of-type(2) > div:nth-of-type(1) > ul:nth-of-type(1) > li:nth-of-type(4)"}],[{"x":198.47265625,"y":2241.40234375,"width":93.125,"height":74.5,"left":198.47265625,"top":2241.40234375,"right":291.59765625,"bottom":2315.90234375,"minX":198.47265625,"maxX":291.59765625,"minY":2241.40234375,"maxY":2315.90234375,"xpath":"/HTML/BODY/SECTION[3]/DIV/DIV[2]/DIV/UL/LI[4]/DIV/SPAN","validSize":true,"positiveCoordinates":true,"selector":"html:nth-of-type(1) > body:nth-of-type(1) > section:nth-of-type(3) > div:nth-of-type(1) > div:nth-of-type(2) > div:nth-of-type(1) > ul:nth-of-type(1) > li:nth-of-type(4) > div:nth-of-type(1) > span:nth-of-type(1)"},{"x":22.69921875,"y":2237.328125,"width":401.6015625,"height":97.78125,"left":22.69921875,"top":2237.328125,"right":424.30078125,"bottom":2335.109375,"minX":22.69921875,"maxX":424.30078125,"minY":2237.328125,"maxY":2335.109375,"xpath":"/HTML/BODY/SECTION[3]/DIV/DIV[2]/DIV/UL/LI[4]","validSize":true,"positiveCoordinates":true,"selector":"html:nth-of-type(1) > body:nth-of-type(1) > section:nth-of-type(3) > div:nth-of-type(1) > div:nth-of-type(2) > div:nth-of-type(1) > ul:nth-of-type(1) > li:nth-of-type(4)"}],[{"x":340.5559997558594,"y":3845.985595703125,"width":159.79165649414062,"height":127.83349609375,"left":340.5559997558594,"top":3845.985595703125,"right":500.34765625,"bottom":3973.819091796875,"minX":340.5559997558594,"maxX":500.34765625,"minY":3845.985595703125,"maxY":3973.819091796875,"xpath":"/HTML/BODY/SECTION[3]/DIV/DIV[2]/DIV/UL/LI[4]/DIV/SPAN","validSize":true,"positiveCoordinates":true,"selector":"html:nth-of-type(1) > body:nth-of-type(1) > section:nth-of-type(3) > div:nth-of-type(1) > div:nth-of-type(2) > div:nth-of-type(1) > ul:nth-of-type(1) > li:nth-of-type(4) > div:nth-of-type(1) > span:nth-of-type(1)"},{"x":38.94921875,"y":3838.994873046875,"width":689.1015625,"height":167.78125,"left":38.94921875,"top":3838.994873046875,"right":728.05078125,"bottom":4006.776123046875,"minX":38.94921875,"maxX":728.05078125,"minY":3838.994873046875,"maxY":4006.776123046875,"xpath":"/HTML/BODY/SECTION[3]/DIV/DIV[2]/DIV/UL/LI[4]","validSize":true,"positiveCoordinates":true,"selector":"html:nth-of-type(1) > body:nth-of-type(1) > section:nth-of-type(3) > div:nth-of-type(1) > div:nth-of-type(2) > div:nth-of-type(1) > ul:nth-of-type(1) > li:nth-of-type(4)"}],[{"x":22.049327850341797,"y":4828.802734375,"width":160.35873794555664,"height":128.287109375,"left":22.049327850341797,"top":4828.802734375,"right":182.40806579589844,"bottom":4957.08984375,"minX":22.049327850341797,"maxX":182.40806579589844,"minY":4828.802734375,"maxY":4957.08984375,"xpath":"/HTML/BODY/SECTION[3]/DIV/DIV[2]/DIV/UL/LI[4]/DIV/SPAN","validSize":true,"positiveCoordinates":true,"selector":"html:nth-of-type(1) > body:nth-of-type(1) > section:nth-of-type(3) > div:nth-of-type(1) > div:nth-of-type(2) > div:nth-of-type(1) > ul:nth-of-type(1) > li:nth-of-type(4) > div:nth-of-type(1) > span:nth-of-type(1)"},{"x":15.033632278442383,"y":4821.787109375,"width":416.93273735046387,"height":148.33154296875,"left":15.033632278442383,"top":4821.787109375,"right":431.96636962890625,"bottom":4970.11865234375,"minX":15.033632278442383,"maxX":431.96636962890625,"minY":4821.787109375,"maxY":4970.11865234375,"xpath":"/HTML/BODY/SECTION[3]/DIV/DIV[2]/DIV/UL/LI[4]","validSize":true,"positiveCoordinates":true,"selector":"html:nth-of-type(1) > body:nth-of-type(1) > section:nth-of-type(3) > div:nth-of-type(1) > div:nth-of-type(2) > div:nth-of-type(1) > ul:nth-of-type(1) > li:nth-of-type(4)"}],[{"x":37.83407974243164,"y":8285.6640625,"width":275.1569480895996,"height":220.125,"left":37.83407974243164,"top":8285.6640625,"right":312.99102783203125,"bottom":8505.7890625,"minX":37.83407974243164,"maxX":312.99102783203125,"minY":8285.6640625,"maxY":8505.7890625,"xpath":"/HTML/BODY/SECTION[3]/DIV/DIV[2]/DIV/UL/LI[4]/DIV/SPAN","validSize":true,"positiveCoordinates":true,"selector":"html:nth-of-type(1) > body:nth-of-type(1) > section:nth-of-type(3) > div:nth-of-type(1) > div:nth-of-type(2) > div:nth-of-type(1) > ul:nth-of-type(1) > li:nth-of-type(4) > div:nth-of-type(1) > span:nth-of-type(1)"},{"x":25.795963287353516,"y":8273.6259765625,"width":715.4080772399902,"height":254.51953125,"left":25.795963287353516,"top":8273.6259765625,"right":741.2040405273438,"bottom":8528.1455078125,"minX":25.795963287353516,"maxX":741.2040405273438,"minY":8273.6259765625,"maxY":8528.1455078125,"xpath":"/HTML/BODY/SECTION[3]/DIV/DIV[2]/DIV/UL/LI[4]","validSize":true,"positiveCoordinates":true,"selector":"html:nth-of-type(1) > body:nth-of-type(1) > section:nth-of-type(3) > div:nth-of-type(1) > div:nth-of-type(2) > div:nth-of-type(1) > ul:nth-of-type(1) > li:nth-of-type(4)"}]],"anonymizedImageNames":["9-447-F","9-767-F","9-447-W","9-767-W","9-447-N","9-767-N"]},{"ID":10,"type":"Element-Collision","rangeMin":320,"rangeMax":767,"rectangles":[[{"x":15,"y":4790,"width":80,"height":80,"left":15,"top":4790,"right":95,"bottom":4870,"minX":15,"maxX":95,"minY":4790,"maxY":4870,"xpath":"/HTML/BODY/SECTION[3]/DIV/DIV[2]/DIV/UL/LI[3]/DIV","validSize":true,"positiveCoordinates":true,"selector":"html:nth-of-type(1) > body:nth-of-type(1) > section:nth-of-type(3) > div:nth-of-type(1) > div:nth-of-type(2) > div:nth-of-type(1) > ul:nth-of-type(1) > li:nth-of-type(3) > div:nth-of-type(1)"},{"x":15,"y":4790,"width":290,"height":232,"left":15,"top":4790,"right":305,"bottom":5022,"minX":15,"maxX":305,"minY":4790,"maxY":5022,"xpath":"/HTML/BODY/SECTION[3]/DIV/DIV[2]/DIV/UL/LI[3]/DIV[2]","validSize":true,"positiveCoordinates":true,"selector":"html:nth-of-type(1) > body:nth-of-type(1) > section:nth-of-type(3) > div:nth-of-type(1) > div:nth-of-type(2) > div:nth-of-type(1) > ul:nth-of-type(1) > li:nth-of-type(3) > div:nth-of-type(2)"}],[{"x":128.5,"y":3750,"width":80,"height":80,"left":128.5,"top":3750,"right":208.5,"bottom":3830,"minX":128.5,"maxX":208.5,"minY":3750,"maxY":3830,"xpath":"/HTML/BODY/SECTION[3]/DIV/DIV[2]/DIV/UL/LI[3]/DIV","validSize":true,"positiveCoordinates":true,"selector":"html:nth-of-type(1) > body:nth-of-type(1) > section:nth-of-type(3) > div:nth-of-type(1) > div:nth-of-type(2) > div:nth-of-type(1) > ul:nth-of-type(1) > li:nth-of-type(3) > div:nth-of-type(1)"},{"x":128.5,"y":3750,"width":510,"height":120,"left":128.5,"top":3750,"right":638.5,"bottom":3870,"minX":128.5,"maxX":638.5,"minY":3750,"maxY":3870,"xpath":"/HTML/BODY/SECTION[3]/DIV/DIV[2]/DIV/UL/LI[3]/DIV[2]","validSize":true,"positiveCoordinates":true,"selector":"html:nth-of-type(1) > body:nth-of-type(1) > section:nth-of-type(3) > div:nth-of-type(1) > div:nth-of-type(2) > div:nth-of-type(1) > ul:nth-of-type(1) > li:nth-of-type(3) > div:nth-of-type(2)"}],[{"x":139.1666717529297,"y":1466.6666259765625,"width":41.666656494140625,"height":41.666748046875,"left":139.1666717529297,"top":1466.6666259765625,"right":180.8333282470703,"bottom":1508.3333740234375,"minX":139.1666717529297,"maxX":180.8333282470703,"minY":1466.6666259765625,"maxY":1508.3333740234375,"xpath":"/HTML/BODY/SECTION[3]/DIV/DIV[2]/DIV/UL/LI[3]/DIV","validSize":true,"positiveCoordinates":true,"selector":"html:nth-of-type(1) > body:nth-of-type(1) > section:nth-of-type(3) > div:nth-of-type(1) > div:nth-of-type(2) > div:nth-of-type(1) > ul:nth-of-type(1) > li:nth-of-type(3) > div:nth-of-type(1)"},{"x":16.25,"y":1466.6666259765625,"width":117.87109375,"height":93.3333740234375,"left":16.25,"top":1466.6666259765625,"right":134.12109375,"bottom":1560,"minX":16.25,"maxX":134.12109375,"minY":1466.6666259765625,"maxY":1560,"xpath":"/HTML/BODY/SECTION[3]/DIV/DIV[2]/DIV/UL/LI[3]/DIV[2]","validSize":true,"positiveCoordinates":true,"selector":"html:nth-of-type(1) > body:nth-of-type(1) > section:nth-of-type(3) > div:nth-of-type(1) > div:nth-of-type(2) > div:nth-of-type(1) > ul:nth-of-type(1) > li:nth-of-type(3) > div:nth-of-type(2)"}],[{"x":333.5650939941406,"y":3515.416748046875,"width":99.86981201171875,"height":99.86962890625,"left":333.5650939941406,"top":3515.416748046875,"right":433.4349060058594,"bottom":3615.286376953125,"minX":333.5650939941406,"maxX":433.4349060058594,"minY":3515.416748046875,"maxY":3615.286376953125,"xpath":"/HTML/BODY/SECTION[3]/DIV/DIV[2]/DIV/UL/LI[3]/DIV","validSize":true,"positiveCoordinates":true,"selector":"html:nth-of-type(1) > body:nth-of-type(1) > section:nth-of-type(3) > div:nth-of-type(1) > div:nth-of-type(2) > div:nth-of-type(1) > ul:nth-of-type(1) > li:nth-of-type(3) > div:nth-of-type(1)"},{"x":38.94921875,"y":3515.416748046875,"width":282.52227783203125,"height":223.708251953125,"left":38.94921875,"top":3515.416748046875,"right":321.47149658203125,"bottom":3739.125,"minX":38.94921875,"maxX":321.47149658203125,"minY":3515.416748046875,"maxY":3739.125,"xpath":"/HTML/BODY/SECTION[3]/DIV/DIV[2]/DIV/UL/LI[3]/DIV[2]","validSize":true,"positiveCoordinates":true,"selector":"html:nth-of-type(1) > body:nth-of-type(1) > section:nth-of-type(3) > div:nth-of-type(1) > div:nth-of-type(2) > div:nth-of-type(1) > ul:nth-of-type(1) > li:nth-of-type(3) > div:nth-of-type(2)"}]],"anonymizedImageNames":["10-320-F","10-767-F","10-320-W","10-767-W"]},{"ID":11,"type":"Element-Protrusion","rangeMin":768,"rangeMax":1199,"rectangles":[[{"x":341,"y":3527,"width":160,"height":128,"left":341,"top":3527,"right":501,"bottom":3655,"minX":341,"maxX":501,"minY":3527,"maxY":3655,"xpath":"/HTML/BODY/SECTION[3]/DIV/DIV[2]/DIV/UL/LI[3]/DIV/SPAN","validSize":true,"positiveCoordinates":true,"selector":"html:nth-of-type(1) > body:nth-of-type(1) > section:nth-of-type(3) > div:nth-of-type(1) > div:nth-of-type(2) > div:nth-of-type(1) > ul:nth-of-type(1) > li:nth-of-type(3) > div:nth-of-type(1) > span:nth-of-type(1)"},{"x":334,"y":3520,"width":100,"height":100,"left":334,"top":3520,"right":434,"bottom":3620,"minX":334,"maxX":434,"minY":3520,"maxY":3620,"xpath":"/HTML/BODY/SECTION[3]/DIV/DIV[2]/DIV/UL/LI[3]/DIV","validSize":true,"positiveCoordinates":true,"selector":"html:nth-of-type(1) > body:nth-of-type(1) > section:nth-of-type(3) > div:nth-of-type(1) > div:nth-of-type(2) > div:nth-of-type(1) > ul:nth-of-type(1) > li:nth-of-type(3) > div:nth-of-type(1)"}],[{"x":531.5,"y":3493,"width":160,"height":128,"left":531.5,"top":3493,"right":691.5,"bottom":3621,"minX":531.5,"maxX":691.5,"minY":3493,"maxY":3621,"xpath":"/HTML/BODY/SECTION[3]/DIV/DIV[2]/DIV/UL/LI[3]/DIV/SPAN","validSize":true,"positiveCoordinates":true,"selector":"html:nth-of-type(1) > body:nth-of-type(1) > section:nth-of-type(3) > div:nth-of-type(1) > div:nth-of-type(2) > div:nth-of-type(1) > ul:nth-of-type(1) > li:nth-of-type(3) > div:nth-of-type(1) > span:nth-of-type(1)"},{"x":524.5,"y":3486,"width":150,"height":150,"left":524.5,"top":3486,"right":674.5,"bottom":3636,"minX":524.5,"maxX":674.5,"minY":3486,"maxY":3636,"xpath":"/HTML/BODY/SECTION[3]/DIV/DIV[2]/DIV/UL/LI[3]/DIV","validSize":true,"positiveCoordinates":true,"selector":"html:nth-of-type(1) > body:nth-of-type(1) > section:nth-of-type(3) > div:nth-of-type(1) > div:nth-of-type(2) > div:nth-of-type(1) > ul:nth-of-type(1) > li:nth-of-type(3) > div:nth-of-type(1)"}],[{"x":334.0799865722656,"y":2243.199951171875,"width":102.4000244140625,"height":81.920166015625,"left":334.0799865722656,"top":2243.199951171875,"right":436.4800109863281,"bottom":2325.1201171875,"minX":334.0799865722656,"maxX":436.4800109863281,"minY":2243.199951171875,"maxY":2325.1201171875,"xpath":"/HTML/BODY/SECTION[3]/DIV/DIV[2]/DIV/UL/LI[3]/DIV/SPAN","validSize":true,"positiveCoordinates":true,"selector":"html:nth-of-type(1) > body:nth-of-type(1) > section:nth-of-type(3) > div:nth-of-type(1) > div:nth-of-type(2) > div:nth-of-type(1) > ul:nth-of-type(1) > li:nth-of-type(3) > div:nth-of-type(1) > span:nth-of-type(1)"},{"x":329.6000061035156,"y":2238.719970703125,"width":108.79998779296875,"height":108.800048828125,"left":329.6000061035156,"top":2238.719970703125,"right":438.3999938964844,"bottom":2347.52001953125,"minX":329.6000061035156,"maxX":438.3999938964844,"minY":2238.719970703125,"maxY":2347.52001953125,"xpath":"/HTML/BODY/SECTION[3]/DIV/DIV[2]/DIV/UL/LI[3]/DIV","validSize":true,"positiveCoordinates":true,"selector":"html:nth-of-type(1) > body:nth-of-type(1) > section:nth-of-type(3) > div:nth-of-type(1) > div:nth-of-type(2) > div:nth-of-type(1) > ul:nth-of-type(1) > li:nth-of-type(3) > div:nth-of-type(1)"}],[{"x":521.5650024414062,"y":3502.0791015625,"width":159.86663818359375,"height":127.893310546875,"left":521.5650024414062,"top":3502.0791015625,"right":681.431640625,"bottom":3629.972412109375,"minX":521.5650024414062,"maxX":681.431640625,"minY":3502.0791015625,"maxY":3629.972412109375,"xpath":"/HTML/BODY/SECTION[3]/DIV/DIV[2]/DIV/UL/LI[3]/DIV/SPAN","validSize":true,"positiveCoordinates":true,"selector":"html:nth-of-type(1) > body:nth-of-type(1) > section:nth-of-type(3) > div:nth-of-type(1) > div:nth-of-type(2) > div:nth-of-type(1) > ul:nth-of-type(1) > li:nth-of-type(3) > div:nth-of-type(1) > span:nth-of-type(1)"},{"x":514.5708618164062,"y":3495.0849609375,"width":169.8582763671875,"height":169.8583984375,"left":514.5708618164062,"top":3495.0849609375,"right":684.4291381835938,"bottom":3664.943359375,"minX":514.5708618164062,"maxX":684.4291381835938,"minY":3495.0849609375,"maxY":3664.943359375,"xpath":"/HTML/BODY/SECTION[3]/DIV/DIV[2]/DIV/UL/LI[3]/DIV","validSize":true,"positiveCoordinates":true,"selector":"html:nth-of-type(1) > body:nth-of-type(1) > section:nth-of-type(3) > div:nth-of-type(1) > div:nth-of-type(2) > div:nth-of-type(1) > ul:nth-of-type(1) > li:nth-of-type(3) > div:nth-of-type(1)"}]],"anonymizedImageNames":["11-768-F","11-1199-F","11-768-W","11-1199-W"]},{"ID":12,"type":"Element-Protrusion","rangeMin":513,"rangeMax":767,"rectangles":[[{"x":22,"y":4523,"width":160,"height":128,"left":22,"top":4523,"right":182,"bottom":4651,"minX":22,"maxX":182,"minY":4523,"maxY":4651,"xpath":"/HTML/BODY/SECTION[3]/DIV/DIV[2]/DIV/UL/LI[3]/DIV/SPAN","validSize":true,"positiveCoordinates":true,"selector":"html:nth-of-type(1) > body:nth-of-type(1) > section:nth-of-type(3) > div:nth-of-type(1) > div:nth-of-type(2) > div:nth-of-type(1) > ul:nth-of-type(1) > li:nth-of-type(3) > div:nth-of-type(1) > span:nth-of-type(1)"},{"x":15,"y":4516,"width":483,"height":120,"left":15,"top":4516,"right":498,"bottom":4636,"minX":15,"maxX":498,"minY":4516,"maxY":4636,"xpath":"/HTML/BODY/SECTION[3]/DIV/DIV[2]/DIV/UL/LI[3]","validSize":true,"positiveCoordinates":true,"selector":"html:nth-of-type(1) > body:nth-of-type(1) > section:nth-of-type(3) > div:nth-of-type(1) > div:nth-of-type(2) > div:nth-of-type(1) > ul:nth-of-type(1) > li:nth-of-type(3)"}],[{"x":135.5,"y":3757,"width":160,"height":128,"left":135.5,"top":3757,"right":295.5,"bottom":3885,"minX":135.5,"maxX":295.5,"minY":3757,"maxY":3885,"xpath":"/HTML/BODY/SECTION[3]/DIV/DIV[2]/DIV/UL/LI[3]/DIV/SPAN","validSize":true,"positiveCoordinates":true,"selector":"html:nth-of-type(1) > body:nth-of-type(1) > section:nth-of-type(3) > div:nth-of-type(1) > div:nth-of-type(2) > div:nth-of-type(1) > ul:nth-of-type(1) > li:nth-of-type(3) > div:nth-of-type(1) > span:nth-of-type(1)"},{"x":128.5,"y":3750,"width":510,"height":120,"left":128.5,"top":3750,"right":638.5,"bottom":3870,"minX":128.5,"maxX":638.5,"minY":3750,"maxY":3870,"xpath":"/HTML/BODY/SECTION[3]/DIV/DIV[2]/DIV/UL/LI[3]","validSize":true,"positiveCoordinates":true,"selector":"html:nth-of-type(1) > body:nth-of-type(1) > section:nth-of-type(3) > div:nth-of-type(1) > div:nth-of-type(2) > div:nth-of-type(1) > ul:nth-of-type(1) > li:nth-of-type(3)"}],[{"x":227.77734375,"y":2355.92578125,"width":106.875,"height":85.5,"left":227.77734375,"top":2355.92578125,"right":334.65234375,"bottom":2441.42578125,"minX":227.77734375,"maxX":334.65234375,"minY":2355.92578125,"maxY":2441.42578125,"xpath":"/HTML/BODY/SECTION[3]/DIV/DIV[2]/DIV/UL/LI[3]/DIV/SPAN","validSize":true,"positiveCoordinates":true,"selector":"html:nth-of-type(1) > body:nth-of-type(1) > section:nth-of-type(3) > div:nth-of-type(1) > div:nth-of-type(2) > div:nth-of-type(1) > ul:nth-of-type(1) > li:nth-of-type(3) > div:nth-of-type(1) > span:nth-of-type(1)"},{"x":26.05078125,"y":2351.25,"width":460.8984375,"height":149.625,"left":26.05078125,"top":2351.25,"right":486.94921875,"bottom":2500.875,"minX":26.05078125,"maxX":486.94921875,"minY":2351.25,"maxY":2500.875,"xpath":"/HTML/BODY/SECTION[3]/DIV/DIV[2]/DIV/UL/LI[3]","validSize":true,"positiveCoordinates":true,"selector":"html:nth-of-type(1) > body:nth-of-type(1) > section:nth-of-type(3) > div:nth-of-type(1) > div:nth-of-type(2) > div:nth-of-type(1) > ul:nth-of-type(1) > li:nth-of-type(3)"}],[{"x":340.5559997558594,"y":3522.407470703125,"width":159.79165649414062,"height":127.83349609375,"left":340.5559997558594,"top":3522.407470703125,"right":500.34765625,"bottom":3650.240966796875,"minX":340.5559997558594,"maxX":500.34765625,"minY":3522.407470703125,"maxY":3650.240966796875,"xpath":"/HTML/BODY/SECTION[3]/DIV/DIV[2]/DIV/UL/LI[3]/DIV/SPAN","validSize":true,"positiveCoordinates":true,"selector":"html:nth-of-type(1) > body:nth-of-type(1) > section:nth-of-type(3) > div:nth-of-type(1) > div:nth-of-type(2) > div:nth-of-type(1) > ul:nth-of-type(1) > li:nth-of-type(3) > div:nth-of-type(1) > span:nth-of-type(1)"},{"x":38.94921875,"y":3515.416748046875,"width":689.1015625,"height":223.708251953125,"left":38.94921875,"top":3515.416748046875,"right":728.05078125,"bottom":3739.125,"minX":38.94921875,"maxX":728.05078125,"minY":3515.416748046875,"maxY":3739.125,"xpath":"/HTML/BODY/SECTION[3]/DIV/DIV[2]/DIV/UL/LI[3]","validSize":true,"positiveCoordinates":true,"selector":"html:nth-of-type(1) > body:nth-of-type(1) > section:nth-of-type(3) > div:nth-of-type(1) > div:nth-of-type(2) > div:nth-of-type(1) > ul:nth-of-type(1) > li:nth-of-type(3)"}],[{"x":22.04296875,"y":4531.833984375,"width":160.3125,"height":128.25,"left":22.04296875,"top":4531.833984375,"right":182.35546875,"bottom":4660.083984375,"minX":22.04296875,"maxX":182.35546875,"minY":4531.833984375,"maxY":4660.083984375,"xpath":"/HTML/BODY/SECTION[3]/DIV/DIV[2]/DIV/UL/LI[3]/DIV/SPAN","validSize":true,"positiveCoordinates":true,"selector":"html:nth-of-type(1) > body:nth-of-type(1) > section:nth-of-type(3) > div:nth-of-type(1) > div:nth-of-type(2) > div:nth-of-type(1) > ul:nth-of-type(1) > li:nth-of-type(3) > div:nth-of-type(1) > span:nth-of-type(1)"},{"x":15.029296875,"y":4524.8203125,"width":482.94140625,"height":148.2890625,"left":15.029296875,"top":4524.8203125,"right":497.970703125,"bottom":4673.109375,"minX":15.029296875,"maxX":497.970703125,"minY":4524.8203125,"maxY":4673.109375,"xpath":"/HTML/BODY/SECTION[3]/DIV/DIV[2]/DIV/UL/LI[3]","validSize":true,"positiveCoordinates":true,"selector":"html:nth-of-type(1) > body:nth-of-type(1) > section:nth-of-type(3) > div:nth-of-type(1) > div:nth-of-type(2) > div:nth-of-type(1) > ul:nth-of-type(1) > li:nth-of-type(3)"}],[{"x":32.95703125,"y":6775.666015625,"width":239.6875,"height":191.75,"left":32.95703125,"top":6775.666015625,"right":272.64453125,"bottom":6967.416015625,"minX":32.95703125,"maxX":272.64453125,"minY":6775.666015625,"maxY":6967.416015625,"xpath":"/HTML/BODY/SECTION[3]/DIV/DIV[2]/DIV/UL/LI[3]/DIV/SPAN","validSize":true,"positiveCoordinates":true,"selector":"html:nth-of-type(1) > body:nth-of-type(1) > section:nth-of-type(3) > div:nth-of-type(1) > div:nth-of-type(2) > div:nth-of-type(1) > ul:nth-of-type(1) > li:nth-of-type(3) > div:nth-of-type(1) > span:nth-of-type(1)"},{"x":22.470703125,"y":6765.1796875,"width":722.05859375,"height":221.7109375,"left":22.470703125,"top":6765.1796875,"right":744.529296875,"bottom":6986.890625,"minX":22.470703125,"maxX":744.529296875,"minY":6765.1796875,"maxY":6986.890625,"xpath":"/HTML/BODY/SECTION[3]/DIV/DIV[2]/DIV/UL/LI[3]","validSize":true,"positiveCoordinates":true,"selector":"html:nth-of-type(1) > body:nth-of-type(1) > section:nth-of-type(3) > div:nth-of-type(1) > div:nth-of-type(2) > div:nth-of-type(1) > ul:nth-of-type(1) > li:nth-of-type(3)"}]],"anonymizedImageNames":["12-513-F","12-767-F","12-513-W","12-767-W","12-513-N","12-767-N"]},{"ID":13,"type":"Element-Collision","rangeMin":320,"rangeMax":767,"rectangles":[[{"x":15,"y":4198,"width":80,"height":80,"left":15,"top":4198,"right":95,"bottom":4278,"minX":15,"maxX":95,"minY":4198,"maxY":4278,"xpath":"/HTML/BODY/SECTION[3]/DIV/DIV[2]/DIV/UL/LI/DIV","validSize":true,"positiveCoordinates":true,"selector":"html:nth-of-type(1) > body:nth-of-type(1) > section:nth-of-type(3) > div:nth-of-type(1) > div:nth-of-type(2) > div:nth-of-type(1) > ul:nth-of-type(1) > li:nth-of-type(1) > div:nth-of-type(1)"},{"x":15,"y":4198,"width":290,"height":260,"left":15,"top":4198,"right":305,"bottom":4458,"minX":15,"maxX":305,"minY":4198,"maxY":4458,"xpath":"/HTML/BODY/SECTION[3]/DIV/DIV[2]/DIV/UL/LI/DIV[2]","validSize":true,"positiveCoordinates":true,"selector":"html:nth-of-type(1) > body:nth-of-type(1) > section:nth-of-type(3) > div:nth-of-type(1) > div:nth-of-type(2) > div:nth-of-type(1) > ul:nth-of-type(1) > li:nth-of-type(1) > div:nth-of-type(2)"}],[{"x":128.5,"y":3410,"width":80,"height":80,"left":128.5,"top":3410,"right":208.5,"bottom":3490,"minX":128.5,"maxX":208.5,"minY":3410,"maxY":3490,"xpath":"/HTML/BODY/SECTION[3]/DIV/DIV[2]/DIV/UL/LI/DIV","validSize":true,"positiveCoordinates":true,"selector":"html:nth-of-type(1) > body:nth-of-type(1) > section:nth-of-type(3) > div:nth-of-type(1) > div:nth-of-type(2) > div:nth-of-type(1) > ul:nth-of-type(1) > li:nth-of-type(1) > div:nth-of-type(1)"},{"x":128.5,"y":3410,"width":510,"height":120,"left":128.5,"top":3410,"right":638.5,"bottom":3530,"minX":128.5,"maxX":638.5,"minY":3410,"maxY":3530,"xpath":"/HTML/BODY/SECTION[3]/DIV/DIV[2]/DIV/UL/LI/DIV[2]","validSize":true,"positiveCoordinates":true,"selector":"html:nth-of-type(1) > body:nth-of-type(1) > section:nth-of-type(3) > div:nth-of-type(1) > div:nth-of-type(2) > div:nth-of-type(1) > ul:nth-of-type(1) > li:nth-of-type(1) > div:nth-of-type(2)"}],[{"x":139.1666717529297,"y":1231.6666259765625,"width":41.666656494140625,"height":41.666748046875,"left":139.1666717529297,"top":1231.6666259765625,"right":180.8333282470703,"bottom":1273.3333740234375,"minX":139.1666717529297,"maxX":180.8333282470703,"minY":1231.6666259765625,"maxY":1273.3333740234375,"xpath":"/HTML/BODY/SECTION[3]/DIV/DIV[2]/DIV/UL/LI/DIV","validSize":true,"positiveCoordinates":true,"selector":"html:nth-of-type(1) > body:nth-of-type(1) > section:nth-of-type(3) > div:nth-of-type(1) > div:nth-of-type(2) > div:nth-of-type(1) > ul:nth-of-type(1) > li:nth-of-type(1) > div:nth-of-type(1)"},{"x":16.25,"y":1231.6666259765625,"width":117.87109375,"height":81.666748046875,"left":16.25,"top":1231.6666259765625,"right":134.12109375,"bottom":1313.3333740234375,"minX":16.25,"maxX":134.12109375,"minY":1231.6666259765625,"maxY":1313.3333740234375,"xpath":"/HTML/BODY/SECTION[3]/DIV/DIV[2]/DIV/UL/LI/DIV[2]","validSize":true,"positiveCoordinates":true,"selector":"html:nth-of-type(1) > body:nth-of-type(1) > section:nth-of-type(3) > div:nth-of-type(1) > div:nth-of-type(2) > div:nth-of-type(1) > ul:nth-of-type(1) > li:nth-of-type(1) > div:nth-of-type(2)"}],[{"x":333.5650939941406,"y":2952.151123046875,"width":99.86981201171875,"height":99.86962890625,"left":333.5650939941406,"top":2952.151123046875,"right":433.4349060058594,"bottom":3052.020751953125,"minX":333.5650939941406,"maxX":433.4349060058594,"minY":2952.151123046875,"maxY":3052.020751953125,"xpath":"/HTML/BODY/SECTION[3]/DIV/DIV[2]/DIV/UL/LI/DIV","validSize":true,"positiveCoordinates":true,"selector":"html:nth-of-type(1) > body:nth-of-type(1) > section:nth-of-type(3) > div:nth-of-type(1) > div:nth-of-type(2) > div:nth-of-type(1) > ul:nth-of-type(1) > li:nth-of-type(1) > div:nth-of-type(1)"},{"x":38.94921875,"y":2952.151123046875,"width":282.52227783203125,"height":195.74462890625,"left":38.94921875,"top":2952.151123046875,"right":321.47149658203125,"bottom":3147.895751953125,"minX":38.94921875,"maxX":321.47149658203125,"minY":2952.151123046875,"maxY":3147.895751953125,"xpath":"/HTML/BODY/SECTION[3]/DIV/DIV[2]/DIV/UL/LI/DIV[2]","validSize":true,"positiveCoordinates":true,"selector":"html:nth-of-type(1) > body:nth-of-type(1) > section:nth-of-type(3) > div:nth-of-type(1) > div:nth-of-type(2) > div:nth-of-type(1) > ul:nth-of-type(1) > li:nth-of-type(1) > div:nth-of-type(2)"}]],"anonymizedImageNames":["13-320-F","13-767-F","13-320-W","13-767-W"]},{"ID":14,"type":"Element-Collision","rangeMin":320,"rangeMax":767,"rectangles":[[{"x":15,"y":4508,"width":80,"height":80,"left":15,"top":4508,"right":95,"bottom":4588,"minX":15,"maxX":95,"minY":4508,"maxY":4588,"xpath":"/HTML/BODY/SECTION[3]/DIV/DIV[2]/DIV/UL/LI[2]/DIV","validSize":true,"positiveCoordinates":true,"selector":"html:nth-of-type(1) > body:nth-of-type(1) > section:nth-of-type(3) > div:nth-of-type(1) > div:nth-of-type(2) > div:nth-of-type(1) > ul:nth-of-type(1) > li:nth-of-type(2) > div:nth-of-type(1)"},{"x":15,"y":4508,"width":290,"height":232,"left":15,"top":4508,"right":305,"bottom":4740,"minX":15,"maxX":305,"minY":4508,"maxY":4740,"xpath":"/HTML/BODY/SECTION[3]/DIV/DIV[2]/DIV/UL/LI[2]/DIV[2]","validSize":true,"positiveCoordinates":true,"selector":"html:nth-of-type(1) > body:nth-of-type(1) > section:nth-of-type(3) > div:nth-of-type(1) > div:nth-of-type(2) > div:nth-of-type(1) > ul:nth-of-type(1) > li:nth-of-type(2) > div:nth-of-type(2)"}],[{"x":128.5,"y":3580,"width":80,"height":80,"left":128.5,"top":3580,"right":208.5,"bottom":3660,"minX":128.5,"maxX":208.5,"minY":3580,"maxY":3660,"xpath":"/HTML/BODY/SECTION[3]/DIV/DIV[2]/DIV/UL/LI[2]/DIV","validSize":true,"positiveCoordinates":true,"selector":"html:nth-of-type(1) > body:nth-of-type(1) > section:nth-of-type(3) > div:nth-of-type(1) > div:nth-of-type(2) > div:nth-of-type(1) > ul:nth-of-type(1) > li:nth-of-type(2) > div:nth-of-type(1)"},{"x":128.5,"y":3580,"width":510,"height":120,"left":128.5,"top":3580,"right":638.5,"bottom":3700,"minX":128.5,"maxX":638.5,"minY":3580,"maxY":3700,"xpath":"/HTML/BODY/SECTION[3]/DIV/DIV[2]/DIV/UL/LI[2]/DIV[2]","validSize":true,"positiveCoordinates":true,"selector":"html:nth-of-type(1) > body:nth-of-type(1) > section:nth-of-type(3) > div:nth-of-type(1) > div:nth-of-type(2) > div:nth-of-type(1) > ul:nth-of-type(1) > li:nth-of-type(2) > div:nth-of-type(2)"}],[{"x":139.1666717529297,"y":1355,"width":41.666656494140625,"height":41.6666259765625,"left":139.1666717529297,"top":1355,"right":180.8333282470703,"bottom":1396.6666259765625,"minX":139.1666717529297,"maxX":180.8333282470703,"minY":1355,"maxY":1396.6666259765625,"xpath":"/HTML/BODY/SECTION[3]/DIV/DIV[2]/DIV/UL/LI[2]/DIV","validSize":true,"positiveCoordinates":true,"selector":"html:nth-of-type(1) > body:nth-of-type(1) > section:nth-of-type(3) > div:nth-of-type(1) > div:nth-of-type(2) > div:nth-of-type(1) > ul:nth-of-type(1) > li:nth-of-type(2) > div:nth-of-type(1)"},{"x":185.87890625,"y":1355,"width":117.87109375,"height":70,"left":185.87890625,"top":1355,"right":303.75,"bottom":1425,"minX":185.87890625,"maxX":303.75,"minY":1355,"maxY":1425,"xpath":"/HTML/BODY/SECTION[3]/DIV/DIV[2]/DIV/UL/LI[2]/DIV[2]","validSize":true,"positiveCoordinates":true,"selector":"html:nth-of-type(1) > body:nth-of-type(1) > section:nth-of-type(3) > div:nth-of-type(1) > div:nth-of-type(2) > div:nth-of-type(1) > ul:nth-of-type(1) > li:nth-of-type(2) > div:nth-of-type(2)"}],[{"x":333.5650939941406,"y":3247.765625,"width":99.86981201171875,"height":99.869873046875,"left":333.5650939941406,"top":3247.765625,"right":433.4349060058594,"bottom":3347.635498046875,"minX":333.5650939941406,"maxX":433.4349060058594,"minY":3247.765625,"maxY":3347.635498046875,"xpath":"/HTML/BODY/SECTION[3]/DIV/DIV[2]/DIV/UL/LI[2]/DIV","validSize":true,"positiveCoordinates":true,"selector":"html:nth-of-type(1) > body:nth-of-type(1) > section:nth-of-type(3) > div:nth-of-type(1) > div:nth-of-type(2) > div:nth-of-type(1) > ul:nth-of-type(1) > li:nth-of-type(2) > div:nth-of-type(1)"},{"x":445.52850341796875,"y":3247.765625,"width":282.52227783203125,"height":167.78125,"left":445.52850341796875,"top":3247.765625,"right":728.05078125,"bottom":3415.546875,"minX":445.52850341796875,"maxX":728.05078125,"minY":3247.765625,"maxY":3415.546875,"xpath":"/HTML/BODY/SECTION[3]/DIV/DIV[2]/DIV/UL/LI[2]/DIV[2]","validSize":true,"positiveCoordinates":true,"selector":"html:nth-of-type(1) > body:nth-of-type(1) > section:nth-of-type(3) > div:nth-of-type(1) > div:nth-of-type(2) > div:nth-of-type(1) > ul:nth-of-type(1) > li:nth-of-type(2) > div:nth-of-type(2)"}]],"anonymizedImageNames":["14-320-F","14-767-F","14-320-W","14-767-W"]},{"ID":15,"type":"Element-Protrusion","rangeMin":768,"rangeMax":1199,"rectangles":[[{"x":341,"y":2963,"width":160,"height":128,"left":341,"top":2963,"right":501,"bottom":3091,"minX":341,"maxX":501,"minY":2963,"maxY":3091,"xpath":"/HTML/BODY/SECTION[3]/DIV/DIV[2]/DIV/UL/LI/DIV/SPAN","validSize":true,"positiveCoordinates":true,"selector":"html:nth-of-type(1) > body:nth-of-type(1) > section:nth-of-type(3) > div:nth-of-type(1) > div:nth-of-type(2) > div:nth-of-type(1) > ul:nth-of-type(1) > li:nth-of-type(1) > div:nth-of-type(1) > span:nth-of-type(1)"},{"x":334,"y":2956,"width":100,"height":100,"left":334,"top":2956,"right":434,"bottom":3056,"minX":334,"maxX":434,"minY":2956,"maxY":3056,"xpath":"/HTML/BODY/SECTION[3]/DIV/DIV[2]/DIV/UL/LI/DIV","validSize":true,"positiveCoordinates":true,"selector":"html:nth-of-type(1) > body:nth-of-type(1) > section:nth-of-type(3) > div:nth-of-type(1) > div:nth-of-type(2) > div:nth-of-type(1) > ul:nth-of-type(1) > li:nth-of-type(1) > div:nth-of-type(1)"}],[{"x":531.5,"y":2993,"width":160,"height":128,"left":531.5,"top":2993,"right":691.5,"bottom":3121,"minX":531.5,"maxX":691.5,"minY":2993,"maxY":3121,"xpath":"/HTML/BODY/SECTION[3]/DIV/DIV[2]/DIV/UL/LI/DIV/SPAN","validSize":true,"positiveCoordinates":true,"selector":"html:nth-of-type(1) > body:nth-of-type(1) > section:nth-of-type(3) > div:nth-of-type(1) > div:nth-of-type(2) > div:nth-of-type(1) > ul:nth-of-type(1) > li:nth-of-type(1) > div:nth-of-type(1) > span:nth-of-type(1)"},{"x":524.5,"y":2986,"width":150,"height":150,"left":524.5,"top":2986,"right":674.5,"bottom":3136,"minX":524.5,"maxX":674.5,"minY":2986,"maxY":3136,"xpath":"/HTML/BODY/SECTION[3]/DIV/DIV[2]/DIV/UL/LI/DIV","validSize":true,"positiveCoordinates":true,"selector":"html:nth-of-type(1) > body:nth-of-type(1) > section:nth-of-type(3) > div:nth-of-type(1) > div:nth-of-type(2) > div:nth-of-type(1) > ul:nth-of-type(1) > li:nth-of-type(1) > div:nth-of-type(1)"}],[{"x":334.0799865722656,"y":1897.5999755859375,"width":102.4000244140625,"height":81.9200439453125,"left":334.0799865722656,"top":1897.5999755859375,"right":436.4800109863281,"bottom":1979.52001953125,"minX":334.0799865722656,"maxX":436.4800109863281,"minY":1897.5999755859375,"maxY":1979.52001953125,"xpath":"/HTML/BODY/SECTION[3]/DIV/DIV[2]/DIV/UL/LI/DIV/SPAN","validSize":true,"positiveCoordinates":true,"selector":"html:nth-of-type(1) > body:nth-of-type(1) > section:nth-of-type(3) > div:nth-of-type(1) > div:nth-of-type(2) > div:nth-of-type(1) > ul:nth-of-type(1) > li:nth-of-type(1) > div:nth-of-type(1) > span:nth-of-type(1)"},{"x":329.6000061035156,"y":1893.1199951171875,"width":108.79998779296875,"height":108.800048828125,"left":329.6000061035156,"top":1893.1199951171875,"right":438.3999938964844,"bottom":2001.9200439453125,"minX":329.6000061035156,"maxX":438.3999938964844,"minY":1893.1199951171875,"maxY":2001.9200439453125,"xpath":"/HTML/BODY/SECTION[3]/DIV/DIV[2]/DIV/UL/LI/DIV","validSize":true,"positiveCoordinates":true,"selector":"html:nth-of-type(1) > body:nth-of-type(1) > section:nth-of-type(3) > div:nth-of-type(1) > div:nth-of-type(2) > div:nth-of-type(1) > ul:nth-of-type(1) > li:nth-of-type(1) > div:nth-of-type(1)"}],[{"x":521.5650024414062,"y":2962.529052734375,"width":159.86663818359375,"height":127.8935546875,"left":521.5650024414062,"top":2962.529052734375,"right":681.431640625,"bottom":3090.422607421875,"minX":521.5650024414062,"maxX":681.431640625,"minY":2962.529052734375,"maxY":3090.422607421875,"xpath":"/HTML/BODY/SECTION[3]/DIV/DIV[2]/DIV/UL/LI/DIV/SPAN","validSize":true,"positiveCoordinates":true,"selector":"html:nth-of-type(1) > body:nth-of-type(1) > section:nth-of-type(3) > div:nth-of-type(1) > div:nth-of-type(2) > div:nth-of-type(1) > ul:nth-of-type(1) > li:nth-of-type(1) > div:nth-of-type(1) > span:nth-of-type(1)"},{"x":514.5708618164062,"y":2955.534912109375,"width":169.8582763671875,"height":169.8583984375,"left":514.5708618164062,"top":2955.534912109375,"right":684.4291381835938,"bottom":3125.393310546875,"minX":514.5708618164062,"maxX":684.4291381835938,"minY":2955.534912109375,"maxY":3125.393310546875,"xpath":"/HTML/BODY/SECTION[3]/DIV/DIV[2]/DIV/UL/LI/DIV","validSize":true,"positiveCoordinates":true,"selector":"html:nth-of-type(1) > body:nth-of-type(1) > section:nth-of-type(3) > div:nth-of-type(1) > div:nth-of-type(2) > div:nth-of-type(1) > ul:nth-of-type(1) > li:nth-of-type(1) > div:nth-of-type(1)"}]],"anonymizedImageNames":["15-768-F","15-1199-F","15-768-W","15-1199-W"]},{"ID":16,"type":"Element-Protrusion","rangeMin":458,"rangeMax":767,"rectangles":[[{"x":22,"y":4252,"width":160,"height":128,"left":22,"top":4252,"right":182,"bottom":4380,"minX":22,"maxX":182,"minY":4252,"maxY":4380,"xpath":"/HTML/BODY/SECTION[3]/DIV/DIV[2]/DIV/UL/LI/DIV/SPAN","validSize":true,"positiveCoordinates":true,"selector":"html:nth-of-type(1) > body:nth-of-type(1) > section:nth-of-type(3) > div:nth-of-type(1) > div:nth-of-type(2) > div:nth-of-type(1) > ul:nth-of-type(1) > li:nth-of-type(1) > div:nth-of-type(1) > span:nth-of-type(1)"},{"x":15,"y":4245,"width":428,"height":120,"left":15,"top":4245,"right":443,"bottom":4365,"minX":15,"maxX":443,"minY":4245,"maxY":4365,"xpath":"/HTML/BODY/SECTION[3]/DIV/DIV[2]/DIV/UL/LI","validSize":true,"positiveCoordinates":true,"selector":"html:nth-of-type(1) > body:nth-of-type(1) > section:nth-of-type(3) > div:nth-of-type(1) > div:nth-of-type(2) > div:nth-of-type(1) > ul:nth-of-type(1) > li:nth-of-type(1)"}],[{"x":135.5,"y":3417,"width":160,"height":128,"left":135.5,"top":3417,"right":295.5,"bottom":3545,"minX":135.5,"maxX":295.5,"minY":3417,"maxY":3545,"xpath":"/HTML/BODY/SECTION[3]/DIV/DIV[2]/DIV/UL/LI/DIV/SPAN","validSize":true,"positiveCoordinates":true,"selector":"html:nth-of-type(1) > body:nth-of-type(1) > section:nth-of-type(3) > div:nth-of-type(1) > div:nth-of-type(2) > div:nth-of-type(1) > ul:nth-of-type(1) > li:nth-of-type(1) > div:nth-of-type(1) > span:nth-of-type(1)"},{"x":128.5,"y":3410,"width":510,"height":120,"left":128.5,"top":3410,"right":638.5,"bottom":3530,"minX":128.5,"maxX":638.5,"minY":3410,"maxY":3530,"xpath":"/HTML/BODY/SECTION[3]/DIV/DIV[2]/DIV/UL/LI","validSize":true,"positiveCoordinates":true,"selector":"html:nth-of-type(1) > body:nth-of-type(1) > section:nth-of-type(3) > div:nth-of-type(1) > div:nth-of-type(2) > div:nth-of-type(1) > ul:nth-of-type(1) > li:nth-of-type(1)"}],[{"x":203.3567657470703,"y":1766.9974365234375,"width":95.41667175292969,"height":76.333251953125,"left":203.3567657470703,"top":1766.9974365234375,"right":298.7734375,"bottom":1843.3306884765625,"minX":203.3567657470703,"maxX":298.7734375,"minY":1766.9974365234375,"maxY":1843.3306884765625,"xpath":"/HTML/BODY/SECTION[3]/DIV/DIV[2]/DIV/UL/LI/DIV/SPAN","validSize":true,"positiveCoordinates":true,"selector":"html:nth-of-type(1) > body:nth-of-type(1) > section:nth-of-type(3) > div:nth-of-type(1) > div:nth-of-type(2) > div:nth-of-type(1) > ul:nth-of-type(1) > li:nth-of-type(1) > div:nth-of-type(1) > span:nth-of-type(1)"},{"x":23.2578125,"y":1762.8228759765625,"width":411.484375,"height":116.885498046875,"left":23.2578125,"top":1762.8228759765625,"right":434.7421875,"bottom":1879.7083740234375,"minX":23.2578125,"maxX":434.7421875,"minY":1762.8228759765625,"maxY":1879.7083740234375,"xpath":"/HTML/BODY/SECTION[3]/DIV/DIV[2]/DIV/UL/LI","validSize":true,"positiveCoordinates":true,"selector":"html:nth-of-type(1) > body:nth-of-type(1) > section:nth-of-type(3) > div:nth-of-type(1) > div:nth-of-type(2) > div:nth-of-type(1) > ul:nth-of-type(1) > li:nth-of-type(1)"}],[{"x":340.5559997558594,"y":2959.141845703125,"width":159.79165649414062,"height":127.83349609375,"left":340.5559997558594,"top":2959.141845703125,"right":500.34765625,"bottom":3086.975341796875,"minX":340.5559997558594,"maxX":500.34765625,"minY":2959.141845703125,"maxY":3086.975341796875,"xpath":"/HTML/BODY/SECTION[3]/DIV/DIV[2]/DIV/UL/LI/DIV/SPAN","validSize":true,"positiveCoordinates":true,"selector":"html:nth-of-type(1) > body:nth-of-type(1) > section:nth-of-type(3) > div:nth-of-type(1) > div:nth-of-type(2) > div:nth-of-type(1) > ul:nth-of-type(1) > li:nth-of-type(1) > div:nth-of-type(1) > span:nth-of-type(1)"},{"x":38.94921875,"y":2952.151123046875,"width":689.1015625,"height":195.74462890625,"left":38.94921875,"top":2952.151123046875,"right":728.05078125,"bottom":3147.895751953125,"minX":38.94921875,"maxX":728.05078125,"minY":2952.151123046875,"maxY":3147.895751953125,"xpath":"/HTML/BODY/SECTION[3]/DIV/DIV[2]/DIV/UL/LI","validSize":true,"positiveCoordinates":true,"selector":"html:nth-of-type(1) > body:nth-of-type(1) > section:nth-of-type(3) > div:nth-of-type(1) > div:nth-of-type(2) > div:nth-of-type(1) > ul:nth-of-type(1) > li:nth-of-type(1)"}],[{"x":22.048139572143555,"y":4261.30419921875,"width":160.3501148223877,"height":128.2802734375,"left":22.048139572143555,"top":4261.30419921875,"right":182.39825439453125,"bottom":4389.58447265625,"minX":22.048139572143555,"maxX":182.39825439453125,"minY":4261.30419921875,"maxY":4389.58447265625,"xpath":"/HTML/BODY/SECTION[3]/DIV/DIV[2]/DIV/UL/LI/DIV/SPAN","validSize":true,"positiveCoordinates":true,"selector":"html:nth-of-type(1) > body:nth-of-type(1) > section:nth-of-type(3) > div:nth-of-type(1) > div:nth-of-type(2) > div:nth-of-type(1) > ul:nth-of-type(1) > li:nth-of-type(1) > div:nth-of-type(1) > span:nth-of-type(1)"},{"x":15.032822608947754,"y":4254.2890625,"width":427.93434047698975,"height":148.32373046875,"left":15.032822608947754,"top":4254.2890625,"right":442.9671630859375,"bottom":4402.61279296875,"minX":15.032822608947754,"maxX":442.9671630859375,"minY":4254.2890625,"maxY":4402.61279296875,"xpath":"/HTML/BODY/SECTION[3]/DIV/DIV[2]/DIV/UL/LI","validSize":true,"positiveCoordinates":true,"selector":"html:nth-of-type(1) > body:nth-of-type(1) > section:nth-of-type(3) > div:nth-of-type(1) > div:nth-of-type(2) > div:nth-of-type(1) > ul:nth-of-type(1) > li:nth-of-type(1)"}],[{"x":36.92341232299805,"y":7136.2890625,"width":268.5339241027832,"height":214.8271484375,"left":36.92341232299805,"top":7136.2890625,"right":305.45733642578125,"bottom":7351.1162109375,"minX":36.92341232299805,"maxX":305.45733642578125,"minY":7136.2890625,"maxY":7351.1162109375,"xpath":"/HTML/BODY/SECTION[3]/DIV/DIV[2]/DIV/UL/LI/DIV/SPAN","validSize":true,"positiveCoordinates":true,"selector":"html:nth-of-type(1) > body:nth-of-type(1) > section:nth-of-type(3) > div:nth-of-type(1) > div:nth-of-type(2) > div:nth-of-type(1) > ul:nth-of-type(1) > li:nth-of-type(1) > div:nth-of-type(1) > span:nth-of-type(1)"},{"x":25.1750545501709,"y":7124.54052734375,"width":716.6498966217041,"height":248.39404296875,"left":25.1750545501709,"top":7124.54052734375,"right":741.824951171875,"bottom":7372.9345703125,"minX":25.1750545501709,"maxX":741.824951171875,"minY":7124.54052734375,"maxY":7372.9345703125,"xpath":"/HTML/BODY/SECTION[3]/DIV/DIV[2]/DIV/UL/LI","validSize":true,"positiveCoordinates":true,"selector":"html:nth-of-type(1) > body:nth-of-type(1) > section:nth-of-type(3) > div:nth-of-type(1) > div:nth-of-type(2) > div:nth-of-type(1) > ul:nth-of-type(1) > li:nth-of-type(1)"}]],"anonymizedImageNames":["16-458-F","16-767-F","16-458-W","16-767-W","16-458-N","16-767-N"]},{"ID":17,"type":"Element-Protrusion","rangeMin":768,"rangeMax":1199,"rectangles":[[{"x":341,"y":3259,"width":160,"height":128,"left":341,"top":3259,"right":501,"bottom":3387,"minX":341,"maxX":501,"minY":3259,"maxY":3387,"xpath":"/HTML/BODY/SECTION[3]/DIV/DIV[2]/DIV/UL/LI[2]/DIV/SPAN","validSize":true,"positiveCoordinates":true,"selector":"html:nth-of-type(1) > body:nth-of-type(1) > section:nth-of-type(3) > div:nth-of-type(1) > div:nth-of-type(2) > div:nth-of-type(1) > ul:nth-of-type(1) > li:nth-of-type(2) > div:nth-of-type(1) > span:nth-of-type(1)"},{"x":334,"y":3252,"width":100,"height":100,"left":334,"top":3252,"right":434,"bottom":3352,"minX":334,"maxX":434,"minY":3252,"maxY":3352,"xpath":"/HTML/BODY/SECTION[3]/DIV/DIV[2]/DIV/UL/LI[2]/DIV","validSize":true,"positiveCoordinates":true,"selector":"html:nth-of-type(1) > body:nth-of-type(1) > section:nth-of-type(3) > div:nth-of-type(1) > div:nth-of-type(2) > div:nth-of-type(1) > ul:nth-of-type(1) > li:nth-of-type(2) > div:nth-of-type(1)"}],[{"x":531.5,"y":3243,"width":160,"height":128,"left":531.5,"top":3243,"right":691.5,"bottom":3371,"minX":531.5,"maxX":691.5,"minY":3243,"maxY":3371,"xpath":"/HTML/BODY/SECTION[3]/DIV/DIV[2]/DIV/UL/LI[2]/DIV/SPAN","validSize":true,"positiveCoordinates":true,"selector":"html:nth-of-type(1) > body:nth-of-type(1) > section:nth-of-type(3) > div:nth-of-type(1) > div:nth-of-type(2) > div:nth-of-type(1) > ul:nth-of-type(1) > li:nth-of-type(2) > div:nth-of-type(1) > span:nth-of-type(1)"},{"x":524.5,"y":3236,"width":150,"height":150,"left":524.5,"top":3236,"right":674.5,"bottom":3386,"minX":524.5,"maxX":674.5,"minY":3236,"maxY":3386,"xpath":"/HTML/BODY/SECTION[3]/DIV/DIV[2]/DIV/UL/LI[2]/DIV","validSize":true,"positiveCoordinates":true,"selector":"html:nth-of-type(1) > body:nth-of-type(1) > section:nth-of-type(3) > div:nth-of-type(1) > div:nth-of-type(2) > div:nth-of-type(1) > ul:nth-of-type(1) > li:nth-of-type(2) > div:nth-of-type(1)"}],[{"x":334.0799865722656,"y":2070.39990234375,"width":102.4000244140625,"height":81.920166015625,"left":334.0799865722656,"top":2070.39990234375,"right":436.4800109863281,"bottom":2152.320068359375,"minX":334.0799865722656,"maxX":436.4800109863281,"minY":2070.39990234375,"maxY":2152.320068359375,"xpath":"/HTML/BODY/SECTION[3]/DIV/DIV[2]/DIV/UL/LI[2]/DIV/SPAN","validSize":true,"positiveCoordinates":true,"selector":"html:nth-of-type(1) > body:nth-of-type(1) > section:nth-of-type(3) > div:nth-of-type(1) > div:nth-of-type(2) > div:nth-of-type(1) > ul:nth-of-type(1) > li:nth-of-type(2) > div:nth-of-type(1) > span:nth-of-type(1)"},{"x":329.6000061035156,"y":2065.919921875,"width":108.79998779296875,"height":108.800048828125,"left":329.6000061035156,"top":2065.919921875,"right":438.3999938964844,"bottom":2174.719970703125,"minX":329.6000061035156,"maxX":438.3999938964844,"minY":2065.919921875,"maxY":2174.719970703125,"xpath":"/HTML/BODY/SECTION[3]/DIV/DIV[2]/DIV/UL/LI[2]/DIV","validSize":true,"positiveCoordinates":true,"selector":"html:nth-of-type(1) > body:nth-of-type(1) > section:nth-of-type(3) > div:nth-of-type(1) > div:nth-of-type(2) > div:nth-of-type(1) > ul:nth-of-type(1) > li:nth-of-type(2) > div:nth-of-type(1)"}],[{"x":521.5650024414062,"y":3232.30419921875,"width":159.86663818359375,"height":127.893310546875,"left":521.5650024414062,"top":3232.30419921875,"right":681.431640625,"bottom":3360.197509765625,"minX":521.5650024414062,"maxX":681.431640625,"minY":3232.30419921875,"maxY":3360.197509765625,"xpath":"/HTML/BODY/SECTION[3]/DIV/DIV[2]/DIV/UL/LI[2]/DIV/SPAN","validSize":true,"positiveCoordinates":true,"selector":"html:nth-of-type(1) > body:nth-of-type(1) > section:nth-of-type(3) > div:nth-of-type(1) > div:nth-of-type(2) > div:nth-of-type(1) > ul:nth-of-type(1) > li:nth-of-type(2) > div:nth-of-type(1) > span:nth-of-type(1)"},{"x":514.5708618164062,"y":3225.31005859375,"width":169.8582763671875,"height":169.858154296875,"left":514.5708618164062,"top":3225.31005859375,"right":684.4291381835938,"bottom":3395.168212890625,"minX":514.5708618164062,"maxX":684.4291381835938,"minY":3225.31005859375,"maxY":3395.168212890625,"xpath":"/HTML/BODY/SECTION[3]/DIV/DIV[2]/DIV/UL/LI[2]/DIV","validSize":true,"positiveCoordinates":true,"selector":"html:nth-of-type(1) > body:nth-of-type(1) > section:nth-of-type(3) > div:nth-of-type(1) > div:nth-of-type(2) > div:nth-of-type(1) > ul:nth-of-type(1) > li:nth-of-type(2) > div:nth-of-type(1)"}]],"anonymizedImageNames":["17-768-F","17-1199-F","17-768-W","17-1199-W"]},{"ID":18,"type":"Element-Protrusion","rangeMin":446,"rangeMax":767,"rectangles":[[{"x":22,"y":4450,"width":160,"height":128,"left":22,"top":4450,"right":182,"bottom":4578,"minX":22,"maxX":182,"minY":4450,"maxY":4578,"xpath":"/HTML/BODY/SECTION[3]/DIV/DIV[2]/DIV/UL/LI[2]/DIV/SPAN","validSize":true,"positiveCoordinates":true,"selector":"html:nth-of-type(1) > body:nth-of-type(1) > section:nth-of-type(3) > div:nth-of-type(1) > div:nth-of-type(2) > div:nth-of-type(1) > ul:nth-of-type(1) > li:nth-of-type(2) > div:nth-of-type(1) > span:nth-of-type(1)"},{"x":15,"y":4443,"width":416,"height":120,"left":15,"top":4443,"right":431,"bottom":4563,"minX":15,"maxX":431,"minY":4443,"maxY":4563,"xpath":"/HTML/BODY/SECTION[3]/DIV/DIV[2]/DIV/UL/LI[2]","validSize":true,"positiveCoordinates":true,"selector":"html:nth-of-type(1) > body:nth-of-type(1) > section:nth-of-type(3) > div:nth-of-type(1) > div:nth-of-type(2) > div:nth-of-type(1) > ul:nth-of-type(1) > li:nth-of-type(2)"}],[{"x":135.5,"y":3587,"width":160,"height":128,"left":135.5,"top":3587,"right":295.5,"bottom":3715,"minX":135.5,"maxX":295.5,"minY":3587,"maxY":3715,"xpath":"/HTML/BODY/SECTION[3]/DIV/DIV[2]/DIV/UL/LI[2]/DIV/SPAN","validSize":true,"positiveCoordinates":true,"selector":"html:nth-of-type(1) > body:nth-of-type(1) > section:nth-of-type(3) > div:nth-of-type(1) > div:nth-of-type(2) > div:nth-of-type(1) > ul:nth-of-type(1) > li:nth-of-type(2) > div:nth-of-type(1) > span:nth-of-type(1)"},{"x":128.5,"y":3580,"width":510,"height":120,"left":128.5,"top":3580,"right":638.5,"bottom":3700,"minX":128.5,"maxX":638.5,"minY":3580,"maxY":3700,"xpath":"/HTML/BODY/SECTION[3]/DIV/DIV[2]/DIV/UL/LI[2]","validSize":true,"positiveCoordinates":true,"selector":"html:nth-of-type(1) > body:nth-of-type(1) > section:nth-of-type(3) > div:nth-of-type(1) > div:nth-of-type(2) > div:nth-of-type(1) > ul:nth-of-type(1) > li:nth-of-type(2)"}],[{"x":198.0286407470703,"y":1892.5963134765625,"width":92.91667175292969,"height":74.3333740234375,"left":198.0286407470703,"top":1892.5963134765625,"right":290.9453125,"bottom":1966.9296875,"minX":198.0286407470703,"maxX":290.9453125,"minY":1892.5963134765625,"maxY":1966.9296875,"xpath":"/HTML/BODY/SECTION[3]/DIV/DIV[2]/DIV/UL/LI[2]/DIV/SPAN","validSize":true,"positiveCoordinates":true,"selector":"html:nth-of-type(1) > body:nth-of-type(1) > section:nth-of-type(3) > div:nth-of-type(1) > div:nth-of-type(2) > div:nth-of-type(1) > ul:nth-of-type(1) > li:nth-of-type(2) > div:nth-of-type(1) > span:nth-of-type(1)"},{"x":22.6484375,"y":1888.53125,"width":400.703125,"height":97.5625,"left":22.6484375,"top":1888.53125,"right":423.3515625,"bottom":1986.09375,"minX":22.6484375,"maxX":423.3515625,"minY":1888.53125,"maxY":1986.09375,"xpath":"/HTML/BODY/SECTION[3]/DIV/DIV[2]/DIV/UL/LI[2]","validSize":true,"positiveCoordinates":true,"selector":"html:nth-of-type(1) > body:nth-of-type(1) > section:nth-of-type(3) > div:nth-of-type(1) > div:nth-of-type(2) > div:nth-of-type(1) > ul:nth-of-type(1) > li:nth-of-type(2)"}],[{"x":340.5559997558594,"y":3254.756591796875,"width":159.79165649414062,"height":127.833251953125,"left":340.5559997558594,"top":3254.756591796875,"right":500.34765625,"bottom":3382.58984375,"minX":340.5559997558594,"maxX":500.34765625,"minY":3254.756591796875,"maxY":3382.58984375,"xpath":"/HTML/BODY/SECTION[3]/DIV/DIV[2]/DIV/UL/LI[2]/DIV/SPAN","validSize":true,"positiveCoordinates":true,"selector":"html:nth-of-type(1) > body:nth-of-type(1) > section:nth-of-type(3) > div:nth-of-type(1) > div:nth-of-type(2) > div:nth-of-type(1) > ul:nth-of-type(1) > li:nth-of-type(2) > div:nth-of-type(1) > span:nth-of-type(1)"},{"x":38.94921875,"y":3247.765625,"width":689.1015625,"height":167.78125,"left":38.94921875,"top":3247.765625,"right":728.05078125,"bottom":3415.546875,"minX":38.94921875,"maxX":728.05078125,"minY":3247.765625,"maxY":3415.546875,"xpath":"/HTML/BODY/SECTION[3]/DIV/DIV[2]/DIV/UL/LI[2]","validSize":true,"positiveCoordinates":true,"selector":"html:nth-of-type(1) > body:nth-of-type(1) > section:nth-of-type(3) > div:nth-of-type(1) > div:nth-of-type(2) > div:nth-of-type(1) > ul:nth-of-type(1) > li:nth-of-type(2)"}],[{"x":22.0494384765625,"y":4460,"width":160.3595428466797,"height":128.28759765625,"left":22.0494384765625,"top":4460,"right":182.4089813232422,"bottom":4588.28759765625,"minX":22.0494384765625,"maxX":182.4089813232422,"minY":4460,"maxY":4588.28759765625,"xpath":"/HTML/BODY/SECTION[3]/DIV/DIV[2]/DIV/UL/LI[2]/DIV/SPAN","validSize":true,"positiveCoordinates":true,"selector":"html:nth-of-type(1) > body:nth-of-type(1) > section:nth-of-type(3) > div:nth-of-type(1) > div:nth-of-type(2) > div:nth-of-type(1) > ul:nth-of-type(1) > li:nth-of-type(2) > div:nth-of-type(1) > span:nth-of-type(1)"},{"x":15.033707618713379,"y":4452.984375,"width":415.9325704574585,"height":148.33251953125,"left":15.033707618713379,"top":4452.984375,"right":430.9662780761719,"bottom":4601.31689453125,"minX":15.033707618713379,"maxX":430.9662780761719,"minY":4452.984375,"maxY":4601.31689453125,"xpath":"/HTML/BODY/SECTION[3]/DIV/DIV[2]/DIV/UL/LI[2]","validSize":true,"positiveCoordinates":true,"selector":"html:nth-of-type(1) > body:nth-of-type(1) > section:nth-of-type(3) > div:nth-of-type(1) > div:nth-of-type(2) > div:nth-of-type(1) > ul:nth-of-type(1) > li:nth-of-type(2)"}],[{"x":37.91910171508789,"y":7670,"width":275.77529525756836,"height":220.6201171875,"left":37.91910171508789,"top":7670,"right":313.69439697265625,"bottom":7890.6201171875,"minX":37.91910171508789,"maxX":313.69439697265625,"minY":7670,"maxY":7890.6201171875,"xpath":"/HTML/BODY/SECTION[3]/DIV/DIV[2]/DIV/UL/LI[2]/DIV/SPAN","validSize":true,"positiveCoordinates":true,"selector":"html:nth-of-type(1) > body:nth-of-type(1) > section:nth-of-type(3) > div:nth-of-type(1) > div:nth-of-type(2) > div:nth-of-type(1) > ul:nth-of-type(1) > li:nth-of-type(2) > div:nth-of-type(1) > span:nth-of-type(1)"},{"x":25.853933334350586,"y":7657.93505859375,"width":715.2921237945557,"height":255.091796875,"left":25.853933334350586,"top":7657.93505859375,"right":741.1460571289062,"bottom":7913.02685546875,"minX":25.853933334350586,"maxX":741.1460571289062,"minY":7657.93505859375,"maxY":7913.02685546875,"xpath":"/HTML/BODY/SECTION[3]/DIV/DIV[2]/DIV/UL/LI[2]","validSize":true,"positiveCoordinates":true,"selector":"html:nth-of-type(1) > body:nth-of-type(1) > section:nth-of-type(3) > div:nth-of-type(1) > div:nth-of-type(2) > div:nth-of-type(1) > ul:nth-of-type(1) > li:nth-of-type(2)"}]],"anonymizedImageNames":["18-446-F","18-767-F","18-446-W","18-767-W","18-446-N","18-767-N"]}]}